Workbook

Sheet ORÇAMENTO SINTÉTICO - SB-A2
B1: ORÇAMENTO SINTÉTICO SEM DESONERAÇÃO FONTE: SANEPAR
B3: #VALUE! | F3: ELABORAÇÃO DE ORÇAMENTO PARA ESTAÇÃO ELEVATÓRIA DE ESGOTO | I3: CIDADE: | K3: Altamira do Paraná | N3: #VALUE!
I4: ESTADO: | K4: Paraná
I5: SISTEMA: | K5: EEE
I6: MICROBACIA / ÁREA: | K6: SB-A2
I7: DATA: | K7: =TODAY() -> 46197
I8: REVISÃO: | K8: R00
I9: ANÁLISE TÉCNICA
I10: ELABORAÇÃO: | K10: Daniel Gama
I11: ENG. RESPONSÁVEL: | K11: Rodrigo A. Zanatta
I12: CREA: | K12: SC-0680240/D
B13: Código | E13: Descrição | G13: Tipo | H13: Origem | I13: Quant. | J13: Un. Med. | K13: Valor Unitário | M13: BDI | N13: Preço Unit. C/ BDI | O13: Custo Total | P13: Preço Total C/ BDI
E14: SERVIÇOS INICIAIS | P14: =P15+P20+P29 -> 16719.939
B15: 001 | E15: CANTEIRO DE OBRAS | P15: =P16+P18 -> 6023.8133
B16: 001.004 | E16: PROTEÇÃO DA ÁREA | K16: =[1]REF_TAB_PREÇOS_SANEPAR!I32 | P16: =SUBTOTAL(9,P17:P17) -> 3526.0111
B17: 001004003 | E17: Tapume de chapa de madeira compensada | G17: Mat | H17: Sanepar | I17: =Memorial!D5 -> 23 | J17: m | K17: =[1]REF_TAB_PREÇOS_SANEPAR!I35 -> 135.68 | M17: =IF(G17="", "", IFERROR(IF(G17="Mat", BDI!C$31, IF(G17="MO", BDI!C$17)), "")) -> 0.1299 | N17: =IF(K17="","",K17*(1+M17)) -> 153.30483 | O17: =K17*I17 -> 3120.64 | P17: =N17*I17 -> 3526.0111
B18: 001.005 | E18: PLACA DE OBRA | K18: =[1]REF_TAB_PREÇOS_SANEPAR!I37 | P18: =SUBTOTAL(9,P19) -> 2497.8021
B19: 001005001 | E19: Em chapa metálica | G19: Mat | H19: Sanepar | I19: 4 | J19: m² | K19: =[1]REF_TAB_PREÇOS_SANEPAR!I38 -> 552.66 | M19: =IF(G19="", "", IFERROR(IF(G19="Mat", BDI!C$31, IF(G19="MO", BDI!C$17)), "")) -> 0.1299 | N19: =IF(K19="","",K19*(1+M19)) -> 624.45053 | O19: =K19*I19 -> 2210.64 | P19: =N19*I19 -> 2497.8021
B20: 002 | E20: SERVIÇOS TÉCNICOS | K20: =[1]REF_TAB_PREÇOS_SANEPAR!I39 | P20: =P21+P23+P25+P27 -> 9702.1655
B21: 002.001 | E21: TOPOGRAFIA E GEODÉSIA - SERVIÇOS | K21: =[1]REF_TAB_PREÇOS_SANEPAR!I40 | P21: =SUBTOTAL(9,P22:P22) -> 86.346264
B22: 002001043 | E22: Locação da obra com auxílio de equipamento topográfico | G22: MO | H22: Sanepar | I22: =Memorial!C10 -> 25.5 | J22: m² | K22: =[1]REF_TAB_PREÇOS_SANEPAR!I83 -> 2.72 | M22: =IF(G22="", "", IFERROR(IF(G22="Mat", BDI!C$31, IF(G22="MO", BDI!C$17)), "")) -> 0.2449 | N22: =IF(K22="","",K22*(1+M22)) -> 3.386128 | O22: =K22*I22 -> 69.36 | P22: =N22*I22 -> 86.346264
B23: 002.004 | E23: SONDAGEM A PERCUSSÃO | K23: =[1]REF_TAB_PREÇOS_SANEPAR!I138 | M23: =IF(G23="", "", IFERROR(IF(G23="Mat", [1]BDI!C$31, IF(G23="MO", [1]BDI!C$17)), "")) | P23: =SUBTOTAL(9,P24:P24) -> 9047.622
B24: 002004002 | E24: Perfuração em solo (SPT) com estadia da equipe | G24: MO | H24: Sanepar | I24: 25 | J24: m | K24: =[1]REF_TAB_PREÇOS_SANEPAR!I140 -> 290.71 | M24: =IF(G24="", "", IFERROR(IF(G24="Mat", [1]BDI!C$31, IF(G24="MO", [1]BDI!C$17)), "")) -> 0.2449 | N24: =IF(K24="","",K24*(1+M24)) -> 361.90488 | O24: =K24*I24 -> 7267.75 | P24: =N24*I24 -> 9047.622
B25: 002.006 | E25: SONDAGEM A TRADO | K25: =[1]REF_TAB_PREÇOS_SANEPAR!I160 | P25: =SUBTOTAL(9,P26:P26) -> 376.33327
B26: 002006001 | E26: Perfuração em solo (trado) sem estadia da equipe - Cidade Pólo | G26: MO | H26: Sanepar | I26: 5 | J26: m | K26: =[1]REF_TAB_PREÇOS_SANEPAR!I161 -> 60.46 | M26: =IF(G26="", "", IFERROR(IF(G26="Mat", BDI!C$31, IF(G26="MO", BDI!C$17)), "")) -> 0.2449 | N26: =IF(K26="","",K26*(1+M26)) -> 75.266654 | O26: =K26*I26 -> 302.3 | P26: =N26*I26 -> 376.33327
B27: 002.007 | E27: CADASTRO DE OBRAS | K27: =[1]REF_TAB_PREÇOS_SANEPAR!I167 | P27: =SUBTOTAL(9,P28:P28) -> 191.86399
B28: 002007005 | E28: Cadastro de obra localizada "As Built" | G28: MO | H28: Sanepar | I28: 1 | J28: ud | K28: =[1]REF_TAB_PREÇOS_SANEPAR!I172 -> 154.12 | M28: =IF(G28="", "", IFERROR(IF(G28="Mat", BDI!C$31, IF(G28="MO", BDI!C$17)), "")) -> 0.2449 | N28: =IF(K28="","",K28*(1+M28)) -> 191.86399 | O28: =K28*I28 -> 154.12 | P28: =N28*I28 -> 191.86399
B29: 003 | E29: SERVIÇOS PRELIMINARES | K29: =[1]REF_TAB_PREÇOS_SANEPAR!I173 | P29: =P30+P32+P35 -> 993.96039
B30: 003.002 | E30: ACESSO PROVISÓRIO | K30: =[1]REF_TAB_PREÇOS_SANEPAR!I184 | P30: =SUBTOTAL(9,P31) -> 37.658225
B31: 003002001 | E31: Acesso provisório | G31: MO | H31: Sanepar | I31: 5 | J31: m² | K31: =[1]REF_TAB_PREÇOS_SANEPAR!I185 -> 6.05 | M31: =IF(G31="", "", IFERROR(IF(G31="Mat", BDI!C$31, IF(G31="MO", BDI!C$17)), "")) -> 0.2449 | N31: =IF(K31="","",K31*(1+M31)) -> 7.531645 | O31: =K31*I31 -> 30.25 | P31: =N31*I31 -> 37.658225
B32: 003.005 | E32: SINALIZAÇÃO DE SEGURANÇA | K32: =[1]REF_TAB_PREÇOS_SANEPAR!I201 | P32: =SUBTOTAL(9,P33:P34) -> 55.613678
B33: 003005001 | E33: Fita plástica | G33: Mat | H33: Sanepar | I33: =Memorial!D5 -> 23 | J33: m | K33: =[1]REF_TAB_PREÇOS_SANEPAR!I202 -> 0.3 | M33: =IF(G33="", "", IFERROR(IF(G33="Mat", BDI!C$31, IF(G33="MO", BDI!C$17)), "")) -> 0.1299 | N33: =IF(K33="","",K33*(1+M33)) -> 0.33897 | O33: =K33*I33 -> 6.9 | P33: =N33*I33 -> 7.79631
B34: 003005004 | E34: Tapume em tela plástica | G34: Mat | H34: Sanepar | I34: =Memorial!D5 -> 23 | J34: m | K34: =[1]REF_TAB_PREÇOS_SANEPAR!I205 -> 1.84 | M34: =IF(G34="", "", IFERROR(IF(G34="Mat", BDI!C$31, IF(G34="MO", BDI!C$17)), "")) -> 0.1299 | N34: =IF(K34="","",K34*(1+M34)) -> 2.079016 | O34: =K34*I34 -> 42.32 | P34: =N34*I34 -> 47.817368
B35: 003.006 | E35: SINALIZAÇÃO DE TRÂNSITO | K35: =[1]REF_TAB_PREÇOS_SANEPAR!I206 | P35: =SUBTOTAL(9,P36:P37) -> 900.68849
B36: 003006001 | E36: Placa de advertência 1,00 x 1,00 m | G36: Mat | H36: Sanepar | I36: 2 | J36: ud | K36: =[1]REF_TAB_PREÇOS_SANEPAR!I207 -> 151.33 | M36: =IF(G36="", "", IFERROR(IF(G36="Mat", BDI!C$31, IF(G36="MO", BDI!C$17)), "")) -> 0.1299 | N36: =IF(K36="","",K36*(1+M36)) -> 170.98777 | O36: =K36*I36 -> 302.66 | P36: =N36*I36 -> 341.97553
B37: 003006002 | E37: Placa de advertência 1,00 x 2,00 m | G37: Mat | H37: Sanepar | I37: 2 | J37: ud | K37: =[1]REF_TAB_PREÇOS_SANEPAR!I208 -> 247.24 | M37: =IF(G37="", "", IFERROR(IF(G37="Mat", BDI!C$31, IF(G37="MO", BDI!C$17)), "")) -> 0.1299 | N37: =IF(K37="","",K37*(1+M37)) -> 279.35648 | O37: =K37*I37 -> 494.48 | P37: =N37*I37 -> 558.71295
E38: POÇO | P38: =P39+P44+P57+P66+P69 -> 220648.92
B39: 004 | E39: MOVIMENTO DE SOLOS | K39: =[1]REF_TAB_PREÇOS_SANEPAR!I249 | P39: =P40+P42 -> 1387.3813
B40: 004.007 | E40: ESCAVAÇÃO MECÂNICA, NÃO EM VALAS, EM QUALQUER TIPO DE SOLO, EXCETO ROCHA | K40: =[1]REF_TAB_PREÇOS_SANEPAR!I296 | P40: =SUBTOTAL(9,P41:P41) -> 874.25592
B41: 004007002 | E41: Solos em geral, profundidade 0 m < h = 4 m | G41: MO | H41: Sanepar | I41: =Memorial!G6 -> 45.9 | J41: m³ | K41: =[1]REF_TAB_PREÇOS_SANEPAR!I298 -> 15.3 | M41: =IF(G41="", "", IFERROR(IF(G41="Mat", BDI!C$31, IF(G41="MO", BDI!C$17)), "")) -> 0.2449 | N41: =IF(K41="","",K41*(1+M41)) -> 19.04697 | O41: =K41*I41 -> 702.27 | P41: =N41*I41 -> 874.25592
B42: 004.015 | E42: COMPACTAÇÃO NÃO EM VALAS | K42: =[1]REF_TAB_PREÇOS_SANEPAR!I330 | P42: =SUBTOTAL(9,P43:P43) -> 513.12537
B43: 004015001 | E43: Sem controle do GC | G43: MO | H43: Sanepar | I43: =I41 -> 45.9 | J43: m³ | K43: =[1]REF_TAB_PREÇOS_SANEPAR!I331 -> 8.98 | M43: =IF(G43="", "", IFERROR(IF(G43="Mat", BDI!C$31, IF(G43="MO", BDI!C$17)), "")) -> 0.2449 | N43: =IF(K43="","",K43*(1+M43)) -> 11.179202 | O43: =K43*I43 -> 412.182 | P43: =N43*I43 -> 513.12537
B44: 005 | E44: FUNDAÇÕES E ESTRUTURA | K44: =[1]REF_TAB_PREÇOS_SANEPAR!I444 | P44: =P45+P47+P49+P51+P53+P55 -> 43476.94
B45: 008.009 | E45: FÔRMA PARA VIGA, PILAR E PAREDE | K45: =[1]REF_TAB_PREÇOS_SANEPAR!I524 | P45: =SUBTOTAL(9,P46:P46) -> 7632.4485
B46: 008009006 | E46: Plana em chapa resinada e= 12 mm | G46: MO | H46: Sanepar | I46: =Memorial!R10 -> 49.72 | J46: m² | K46: =[1]REF_TAB_PREÇOS_SANEPAR!I530 -> 123.31 | M46: =IF(G46="", "", IFERROR(IF(G46="Mat", [1]BDI!C$31, IF(G46="MO", [1]BDI!C$17)), "")) -> 0.2449 | N46: =IF(K46="","",K46*(1+M46)) -> 153.50862 | O46: =K46*I46 -> 6130.9732 | P46: =N46*I46 -> 7632.4485
B47: 008.019 | E47: ARMADURA | K47: =[1]REF_TAB_PREÇOS_SANEPAR!I575 | N47: =IF(K47="","",K47*(1+M47)) | P47: =SUBTOTAL(9,P48:P48) -> 15620.87
B48: 008019001 | E48: Em aço CA-50 | G48: MO | H48: Sanepar | I48: =Memorial!R11 -> 816.92 | J48: kg | K48: =[1]REF_TAB_PREÇOS_SANEPAR!I576 -> 15.36 | M48: =IF(G48="", "", IFERROR(IF(G48="Mat", [1]BDI!C$31, IF(G48="MO", [1]BDI!C$17)), "")) -> 0.2449 | N48: =IF(K48="","",K48*(1+M48)) -> 19.121664 | O48: =K48*I48 -> 12547.891 | P48: =N48*I48 -> 15620.87
B49: 008.021 | E49: CONCRETO CONVENCIONAL | K49: =[1]REF_TAB_PREÇOS_SANEPAR!I585 | P49: =SUBTOTAL(9,P50:P50) -> 526.75354
B50: 008021002 | E50: fck = 15,0 MPa | G50: MO | H50: Sanepar | I50: =Memorial!R13 -> 0.52 | J50: m³ | K50: =[1]REF_TAB_PREÇOS_SANEPAR!I587 -> 813.71 | M50: =IF(G50="", "", IFERROR(IF(G50="Mat", [1]BDI!C$31, IF(G50="MO", [1]BDI!C$17)), "")) -> 0.2449 | N50: =IF(K50="","",K50*(1+M50)) -> 1012.9876 | O50: =K50*I50 -> 423.1292 | P50: =N50*I50 -> 526.75354
B51: 008.022 | E51: CONCRETO USINADO | K51: =[1]REF_TAB_PREÇOS_SANEPAR!I594 | P51: =SUBTOTAL(9,P52:P52) -> 7803.721
B52: 008022021 | E52: fck = 40,0 MPa - slump 12 | G52: MO | H52: Sanepar | I52: =Memorial!R12 -> 9.73 | J52: m³ | K52: =[1]REF_TAB_PREÇOS_SANEPAR!I614 -> 644.25 | M52: =IF(G52="", "", IFERROR(IF(G52="Mat", [1]BDI!C$31, IF(G52="MO", [1]BDI!C$17)), "")) -> 0.2449 | N52: =IF(K52="","",K52*(1+M52)) -> 802.02682 | O52: =K52*I52 -> 6268.5525 | P52: =N52*I52 -> 7803.721
B53: 008.023 | E53: BOMBEAMENTO DE CONCRETO | K53: =[1]REF_TAB_PREÇOS_SANEPAR!I619 | P53: =SUBTOTAL(9,P54) -> 639.19652
B54: 008023001 | E54: Bombeamento de concreto usinado | G54: MO | H54: Sanepar | I54: =I52 -> 9.73 | J54: m³ | K54: =[1]REF_TAB_PREÇOS_SANEPAR!I620 -> 52.77 | M54: =IF(G54="", "", IFERROR(IF(G54="Mat", [1]BDI!C$31, IF(G54="MO", [1]BDI!C$17)), "")) -> 0.2449 | N54: =IF(K54="","",K54*(1+M54)) -> 65.693373 | O54: =K54*I54 -> 513.4521 | P54: =N54*I54 -> 639.19652
B55: 008.030 | E55: PROTEÇÃO E IMPERMEABILIZAÇÃO DAS ESTRUTURAS DE CONCRETO | K55: =[1]REF_TAB_PREÇOS_SANEPAR!I646 | P55: =SUBTOTAL(9,P56:P56) -> 11253.951
B56: 008030002 | E56: Impermeabilização flexível com poliuretano | G56: MO | H56: Sanepar | I56: =Memorial!L19 -> 40.08 | J56: m² | K56: =[1]REF_TAB_PREÇOS_SANEPAR!I648 -> 225.55 | M56: =IF(G56="", "", IFERROR(IF(G56="Mat", [1]BDI!C$31, IF(G56="MO", [1]BDI!C$17)), "")) -> 0.2449 | N56: =IF(K56="","",K56*(1+M56)) -> 280.78719 | O56: =K56*I56 -> 9040.044 | P56: =N56*I56 -> 11253.951
B57: 006 | E57: ASSENTAMENTOS | K57: =[1]REF_TAB_PREÇOS_SANEPAR!I673 | P57: =P58+P60+P63 -> 4902.3184
B58: 009.004 | E58: TUBULAÇÃO DE PEAD | K58: =[1]REF_TAB_PREÇOS_SANEPAR!I708 | P58: =SUBTOTAL(9,P59:P59) -> 32.043726
B59: 009004012 | E59: DE 160 mm | G59: MO | H59: Sanepar | I59: 6 | J59: m | K59: =[1]REF_TAB_PREÇOS_SANEPAR!I720 -> 4.29 | M59: =IF(G59="", "", IFERROR(IF(G59="Mat", [1]BDI!C$31, IF(G59="MO", [1]BDI!C$17)), "")) -> 0.2449 | N59: =IF(K59="","",K59*(1+M59)) -> 5.340621 | O59: =K59*I59 -> 25.74 | P59: =N59*I59 -> 32.043726
B60: 009.007 | E60: TUBULAÇÃO DE FERRO DÚCTIL JE/JE2GS/JTI | K60: =[1]REF_TAB_PREÇOS_SANEPAR!I763 | P60: =SUBTOTAL(9,P61:P62) -> 40.340984
B61: 009007001 | E61: DN 80 | G61: MO | H61: Sanepar | I61: =0.5+0.7+1.2+0.7+0.9 -> 4 | J61: m | K61: =[1]REF_TAB_PREÇOS_SANEPAR!I764 -> 7.23 | M61: =IF(G61="", "", IFERROR(IF(G61="Mat", [1]BDI!C$31, IF(G61="MO", [1]BDI!C$17)), "")) -> 0.2449 | N61: =IF(K61="","",K61*(1+M61)) -> 9.000627 | O61: =K61*I61 -> 28.92 | P61: =N61*I61 -> 36.002508
B62: 009007003 | E62: DN 150 | G62: MO | H62: Sanepar | I62: =0.25 -> 0.25 | J62: m | K62: =[1]REF_TAB_PREÇOS_SANEPAR!I766 -> 13.94 | M62: =IF(G62="", "", IFERROR(IF(G62="Mat", [1]BDI!C$31, IF(G62="MO", [1]BDI!C$17)), "")) -> 0.2449 | N62: =IF(K62="","",K62*(1+M62)) -> 17.353906 | O62: =K62*I62 -> 3.485 | P62: =N62*I62 -> 4.3384765
B63: 009.018 | E63: POÇO DE VISITA TIPO D - DN 1200 | K63: =[1]REF_TAB_PREÇOS_SANEPAR!I841 | P63: =SUBTOTAL(9,P64:P65) -> 4829.9336
B64: 009018001 | E64: Para profundidade até 2,00 m | G64: MO | H64: Sanepar | I64: 1 | J64: ud | K64: =[1]REF_TAB_PREÇOS_SANEPAR!I842 -> 3473.34 | M64: =IF(G64="", "", IFERROR(IF(G64="Mat", [1]BDI!C$31, IF(G64="MO", [1]BDI!C$17)), "")) -> 0.2449 | N64: =IF(K64="","",K64*(1+M64)) -> 4323.961 | O64: =K64*I64 -> 3473.34 | P64: =N64*I64 -> 4323.961
B65: 009018002 | E65: Acréscimo para prof. superior a 2,00 m | G65: MO | H65: Sanepar | I65: =(0.31+2.05)-2 -> 0.36 | J65: m | K65: =[1]REF_TAB_PREÇOS_SANEPAR!I843 -> 1128.99 | M65: =IF(G65="", "", IFERROR(IF(G65="Mat", [1]BDI!C$31, IF(G65="MO", [1]BDI!C$17)), "")) -> 0.2449 | N65: =IF(K65="","",K65*(1+M65)) -> 1405.4797 | O65: =K65*I65 -> 406.4364 | P65: =N65*I65 -> 505.97267
B66: 007 | E66: PAVIMENTAÇÃO | K66: =[1]REF_TAB_PREÇOS_SANEPAR!I886 | P66: =P67 -> 1397.2064
B67: 010.002 | E67: EXECUÇÃO DE PAVIMENTOS, GUIAS E SARJETAS | K67: =[1]REF_TAB_PREÇOS_SANEPAR!I911 | M67: =IF(G67="", "", IFERROR(IF(G67="Mat", [1]BDI!C$31, IF(G67="MO", [1]BDI!C$17)), "")) | P67: =SUBTOTAL(9,P68:P68) -> 1397.2064
B68: 010002027 | E68: Revestimento com piso de concreto desempenado | G68: MO | H68: Sanepar | I68: =Memorial!G12 -> 1.275 | J68: m³ | K68: =[1]REF_TAB_PREÇOS_SANEPAR!I938 -> 880.27 | M68: =IF(G68="", "", IFERROR(IF(G68="Mat", [1]BDI!C$31, IF(G68="MO", [1]BDI!C$17)), "")) -> 0.2449 | N68: =IF(K68="","",K68*(1+M68)) -> 1095.8481 | O68: =K68*I68 -> 1122.3443 | P68: =N68*I68 -> 1397.2064
B69: 008 | E69: INSTALAÇÕES DE PRODUÇÃO | P69: =P70+P72+P74+P77 -> 169485.07
B70: 014.001 | E70: INSTALAÇÃO DE CONJUNTO MOTO BOMBA | P70: =SUBTOTAL(9,P71:P71) -> 672.07171
B71: 014001001 | E71: Cmb submerso (poço profundo) até 10 CV | G71: MO | H71: Sanepar | I71: 1 | J71: ud | K71: 539.86 | M71: =IF(G71="", "", IFERROR(IF(G71="Mat", [1]BDI!C$31, IF(G71="MO", [1]BDI!C$17)), "")) -> 0.2449 | N71: =IF(K71="","",K71*(1+M71)) -> 672.07171 | O71: =K71*I71 -> 539.86 | P71: =N71*I71 -> 672.07171
B72: 014.004 | E72: INSTALAÇÃO DE VÁLVULA | P72: =SUBTOTAL(9,P73:P73) -> 112.99957
B73: 014004064 | E73: Válvula entre flanges até DN 200 | G73: MO | H73: Sanepar | I73: 1 | J73: ud | K73: 90.77 | M73: =IF(G73="", "", IFERROR(IF(G73="Mat", [1]BDI!C$31, IF(G73="MO", [1]BDI!C$17)), "")) -> 0.2449 | N73: =IF(K73="","",K73*(1+M73)) -> 112.99957 | O73: =K73*I73 -> 90.77 | P73: =N73*I73 -> 112.99957
B74: 014.044 | E74: MONTAGEM DE TUBULAÇÃO FD | P74: =SUBTOTAL(9,P75:P76) -> 1444.1338
B75: 014044029 | E75: Tubo e conexão FD JF PN-10 DN 80 | G75: MO | H75: Sanepar | I75: 9 | J75: ud | K75: 113.73 | M75: =IF(G75="", "", IFERROR(IF(G75="Mat", BDI!C$31, IF(G75="MO", BDI!C$17)), "")) -> 0.2449 | N75: =IF(K75="","",K75*(1+M75)) -> 141.58248 | O75: =K75*I75 -> 1023.57 | P75: =N75*I75 -> 1274.2423
B76: 014044031 | E76: Tubo e conexão FD JF PN-10 DN 150 | G76: MO | H76: Sanepar | I76: 1 | J76: ud | K76: 136.47 | M76: =IF(G76="", "", IFERROR(IF(G76="Mat", BDI!C$31, IF(G76="MO", BDI!C$17)), "")) -> 0.2449 | N76: =IF(K76="","",K76*(1+M76)) -> 169.8915 | O76: =K76*I76 -> 136.47 | P76: =N76*I76 -> 169.8915
B77: 014.046 | E77: INSTALAÇÕES PEAD/FD/PPR | M77: =IF(G77="", "", IFERROR(IF(G77="Mat", BDI!C$31, IF(G77="MO", BDI!C$17)), "")) | P77: =SUM(P78:P105) -> 167255.87
B78: 19.001 | E78: Tubo polietileno pe 100 pn10 faixa ocre para esgoto (barra com 6,0 m) de160 - l=1600 mm | G78: Mat | H78: CP | I78: 1 | J78: ud | K78: 135.02 | M78: =IF(G78="", "", IFERROR(IF(G78="Mat", [3]BDI!C$31, IF(G78="MO", [3]BDI!C$17)), "")) -> 0.1299 | N78: =IF(K78="","",K78*(1+M78)) -> 152.5591 | O78: =K78*I78 -> 135.02 | P78: =N78*I78 -> 152.5591
B79: =B78+1 -> 19002 | E79: Colarinho polietileno injetado termofusao pe 100 pn10 de160 | G79: Mat | H79: CP | I79: 1 | J79: ud | K79: 314.589 | M79: =IF(G79="", "", IFERROR(IF(G79="Mat", [3]BDI!C$31, IF(G79="MO", [3]BDI!C$17)), "")) -> 0.1299 | N79: =IF(K79="","",K79*(1+M79)) -> 355.45411 | O79: =K79*I79 -> 314.589 | P79: =N79*I79 -> 355.45411
B80: =B79+1 -> 19003 | E80: Toco de tubo fd ff pn10 medindo 0.25m para esgoto dn150 | G80: Mat | H80: CP | I80: 1 | J80: ud | K80: 712.96 | M80: =IF(G80="", "", IFERROR(IF(G80="Mat", [3]BDI!C$31, IF(G80="MO", [3]BDI!C$17)), "")) -> 0.1299 | N80: =IF(K80="","",K80*(1+M80)) -> 805.5735 | O80: =K80*I80 -> 712.96 | P80: =N80*I80 -> 805.5735
B81: =B80+1 -> 19004 | E81: Conjunto motobomba em linha (Q=3,5l/s; H=9,97mca) e conjunto motobomba submersivelq=22,9 m3/h | G81: Mat | H81: CP | I81: 1 | J81: cj | K81: 118259.86 | M81: =IF(G81="", "", IFERROR(IF(G81="Mat", [3]BDI!C$31, IF(G81="MO", [3]BDI!C$17)), "")) -> 0.1299 | N81: =IF(K81="","",K81*(1+M81)) -> 133621.82 | O81: =K81*I81 -> 118259.86 | P81: =N81*I81 -> 133621.82
B82: =B81+1 -> 19005 | E82: Te reducao fd fff para esgoto dn100 dn80 | G82: Mat | H82: CP | I82: 1 | J82: ud | K82: 666.2 | M82: =IF(G82="", "", IFERROR(IF(G82="Mat", [3]BDI!C$31, IF(G82="MO", [3]BDI!C$17)), "")) -> 0.1299 | N82: =IF(K82="","",K82*(1+M82)) -> 752.73938 | O82: =K82*I82 -> 666.2 | P82: =N82*I82 -> 752.73938
B83: =B82+1 -> 19006 | E83: Ventosa combinada/triplice funcao para esgoto corpo em prfv ou nylon reforcado com capacidade vazao minima a 0,4 bar de 220,0 m3/h flange pn10/16 dn100 pol4” | G83: Mat | H83: CP | I83: 1 | J83: ud | K83: 13838 | M83: =IF(G83="", "", IFERROR(IF(G83="Mat", [3]BDI!C$31, IF(G83="MO", [3]BDI!C$17)), "")) -> 0.1299 | N83: =IF(K83="","",K83*(1+M83)) -> 15635.556 | O83: =K83*I83 -> 13838 | P83: =N83*I83 -> 15635.556
B84: =B83+1 -> 19007 | E84: Te fd fff para pn16 esgoto dn80 | G84: Mat | H84: CP | I84: 1 | J84: ud | K84: 579.82 | M84: =IF(G84="", "", IFERROR(IF(G84="Mat", [3]BDI!C$31, IF(G84="MO", [3]BDI!C$17)), "")) -> 0.1299 | N84: =IF(K84="","",K84*(1+M84)) -> 655.13862 | O84: =K84*I84 -> 579.82 | P84: =N84*I84 -> 655.13862
B85: =B84+1 -> 19008 | E85: Toco de tubo fd ff 700mm com aba de vedacao pn16 para esgoto dn80 | G85: Mat | H85: CP | I85: 1 | J85: ud | K85: 1679.95 | M85: =IF(G85="", "", IFERROR(IF(G85="Mat", [3]BDI!C$31, IF(G85="MO", [3]BDI!C$17)), "")) -> 0.1299 | N85: =IF(K85="","",K85*(1+M85)) -> 1898.1755 | O85: =K85*I85 -> 1679.95 | P85: =N85*I85 -> 1898.1755
B86: =B85+1 -> 19009 | E86: Colarinho polietileno injetado termofusao pe 100 pn10 de90 | G86: Mat | H86: CP | I86: 1 | J86: ud | K86: 110.69 | M86: =IF(G86="", "", IFERROR(IF(G86="Mat", [3]BDI!C$31, IF(G86="MO", [3]BDI!C$17)), "")) -> 0.1299 | N86: =IF(K86="","",K86*(1+M86)) -> 125.06863 | O86: =K86*I86 -> 110.69 | P86: =N86*I86 -> 125.06863
B87: =B86+1 -> 19010 | E87: Valvula guilhotina bidirecional fd lug/semilug/wafer manual castelo quadrado e volante para esgoto/agua bruta 16 bar furacao pn16 dn80 | G87: Mat | H87: CP | I87: 1 | J87: ud | K87: 1917 | M87: =IF(G87="", "", IFERROR(IF(G87="Mat", [3]BDI!C$31, IF(G87="MO", [3]BDI!C$17)), "")) -> 0.1299 | N87: =IF(K87="","",K87*(1+M87)) -> 2166.0183 | O87: =K87*I87 -> 1917 | P87: =N87*I87 -> 2166.0183
B88: =B87+1 -> 19011 | E88: Tubo fd k9 ff (solda interferencia) para esgoto pn16 medindo 1,20m dn80 | G88: Mat | H88: CP | I88: 1 | J88: ud | K88: 997.55 | M88: =IF(G88="", "", IFERROR(IF(G88="Mat", [3]BDI!C$31, IF(G88="MO", [3]BDI!C$17)), "")) -> 0.1299 | N88: =IF(K88="","",K88*(1+M88)) -> 1127.1317 | O88: =K88*I88 -> 997.55 | P88: =N88*I88 -> 1127.1317
B89: =B88+1 -> 19012 | E89: Extremidade fd pf 700mm com aba de vedacao para esgoto pn16 dn80 | G89: Mat | H89: CP | I89: 1 | J89: ud | K89: 1679.95 | M89: =IF(G89="", "", IFERROR(IF(G89="Mat", [3]BDI!C$31, IF(G89="MO", [3]BDI!C$17)), "")) -> 0.1299 | N89: =IF(K89="","",K89*(1+M89)) -> 1898.1755 | O89: =K89*I89 -> 1679.95 | P89: =N89*I89 -> 1898.1755
B90: =B89+1 -> 19013 | E90: Curva fd je 2gs bb 22 para esgoto dn80 | G90: Mat | H90: CP | I90: 1 | J90: ud | K90: 655.91 | M90: =IF(G90="", "", IFERROR(IF(G90="Mat", [3]BDI!C$31, IF(G90="MO", [3]BDI!C$17)), "")) -> 0.1299 | N90: =IF(K90="","",K90*(1+M90)) -> 741.11271 | O90: =K90*I90 -> 655.91 | P90: =N90*I90 -> 741.11271
... B103: =B102+1 -> 19026 | E103: Kit parafuso porca arruela lisa aco carbono arruela vedacao furacao para esgoto pn16 nbr 7675 dn100 | G103: Mat | H103: CP | I103: 2 | J103: cj | K103: 135.11 | M103: =IF(G103="", "", IFERROR(IF(G103="Mat", [3]BDI!C$31, IF(G103="MO", [3]BDI!C$17)), "")) -> 0.1299 | N103: =IF(K103="","",K103*(1+M103)) -> 152.66079 | O103: =K103*I103 -> 270.22 | P103: =N103*I103 -> 305.32158
B104: 19039 | E104: Kit parafuso porca arruela lisa aco inox arruela vedacao furacao para esgoto pn10 nbr 7675 dn150 | G104: Mat | H104: CP | I104: 1 | J104: cj | K104: 200.21 | M104: =IF(G104="", "", IFERROR(IF(G104="Mat", [3]BDI!C$31, IF(G104="MO", [3]BDI!C$17)), "")) -> 0.1299 | N104: =IF(K104="","",K104*(1+M104)) -> 226.21728 | O104: =K104*I104 -> 200.21 | P104: =N104*I104 -> 226.21728
B105: =B104+1 -> 19040 | E105: Escada tipo marinheiro PRFV sem gaiola altura menor que 3,5m | G105: Mat | H105: CP | I105: 1 | J105: ud | K105: 1349.64 | M105: =IF(G105="", "", IFERROR(IF(G105="Mat", BDI!C$31, IF(G105="MO", BDI!C$17)), "")) -> 0.1299 | N105: =IF(K105="","",K105*(1+M105)) -> 1524.9582 | O105: =K105*I105 -> 1349.64 | P105: =N105*I105 -> 1524.9582
E106: POÇO DE VISITA | P106: =P107+P112+P123 -> 10421.087
B107: 009 | E107: MOVIMENTO DE SOLOS | P107: =P108+P110 -> 345.78741
B108: 004.007 | E108: ESCAVAÇÃO MECÂNICA, NÃO EM VALAS, EM QUALQUER TIPO DE SOLO, EXCETO ROCHA | K108: =[1]REF_TAB_PREÇOS_SANEPAR!I338 | P108: =SUBTOTAL(9,P109:P109) -> 217.89734
B109: 004007002 | E109: Solos em geral, profundidade 0 m < h = 4 m | G109: MO | H109: Sanepar | I109: =Memorial!P6 -> 11.44 | J109: m³ | K109: 15.3 | M109: =IF(G109="", "", IFERROR(IF(G109="Mat", BDI!C$31, IF(G109="MO", BDI!C$17)), "")) -> 0.2449 | N109: =IF(K109="","",K109*(1+M109)) -> 19.04697 | O109: =K109*I109 -> 175.032 | P109: =N109*I109 -> 217.89734
B110: 004.015 | E110: COMPACTAÇÃO NÃO EM VALAS | P110: =P111 -> 127.89007
B111: 004015001 | E111: Sem controle do GC | G111: MO | H111: Sanepar | I111: =I109 -> 11.44 | J111: m³ | K111: 8.98 | M111: =IF(G111="", "", IFERROR(IF(G111="Mat", BDI!C$31, IF(G111="MO", BDI!C$17)), "")) -> 0.2449 | N111: =IF(K111="","",K111*(1+M111)) -> 11.179202 | O111: =K111*I111 -> 102.7312 | P111: =N111*I111 -> 127.89007
B112: 010 | E112: FUNDAÇÕES E ESTRUTURA | P112: =P115+P117+P119+P121 -> 4039.1013
B113: 008.009 | E113: FÔRMA PARA VIGA, PILAR E PAREDE | P113: =P114 -> 1842.1034
...

Sheet BDI
A1: COMPOSIÇÃO DE BDI E BASE DE PREÇOS | E1: CUSTO DIRETO: | F1: ='ORÇAMENTO SINTÉTICO - PA4'!O305 -> 344407.41
A2: COMPOSIÇÃO DO BDI PARA MODALIDADE A PREÇO UNITÁRIO
A3: BASE DE CÁLCULO: Acórdão nº 2.622/2013 - TCU Plenário (TC 036.076/2011-2) FÓRMULA: Onde: BDI = LDI: bonificações e despesas indiretas (BDI) ou lucros e despesas indretas (LDI) AC: Taxa de rateio da administração central S: Taxa representativa de seguros R: Riscos e imprevistos G: Taxa que representa o ônus das garantias exigidas em edital DF: Taxa representativa das despesas financeiras L: Remuneração bruta do construtor I: Taxa representativa dos tributos CP: Tributos (COFINS e PIS) ISS: Tributos (ISS, variável de acordo com o município) CPRB: Tributos (Contribuição Previdenciária sobre a Receita Bruta)
AF4: Largura Vala | AG4: =(AG5+AG6+AG7+AG8) -> 0.5
A5: COMPOSIÇÃO DO BDI 1 - OBRAS E SERVIÇOS | AF5: Diâmetro | AG5: 0.15
A6: CONSTRUÇÃO DE REDES DE ABASTECIMENTO DE ÁGUA, COLETA DE ESGOTO E CONSTRUÇÕES CORRELATAS | AF6: SL | AG6: 0.35
A7: SIGLA | B7: DISCRIMINAÇÃO DAS PARCELAS | C7: BDI - SEM DESONERAÇÃO | AF7: X
A8: AC | B8: Administração Central | C8: {=_xlfn.IFS($F$1<=150000,0.055,$F$1<=1500000,0.05,$F$1>1500000,0.035)} -> 0.05 | AF8: Y | AG8: 0
A9: SG | B9: Seguro e Garantia | C9: {=_xlfn.IFS($F$1<=150000,0.007,$F$1<=1500000,0.005,$F$1>1500000,0.0035)} -> 0.005
A10: R | B10: Risco | C10: {=_xlfn.IFS($F$1<=150000,0.015,$F$1<=1500000,0.013,$F$1>1500000,0.01)} -> 0.013
A11: DF | B11: Despesas Financeiras | C11: {=_xlfn.IFS($F$1<=150000,0.008,$F$1<=1500000,0.0075,$F$1>1500000,0.007)} -> 0.0075
A12: L | B12: Lucro | C12: {=_xlfn.IFS($F$1<=150000,0.085,$F$1<=1500000,0.08,$F$1>1500000,0.065)} -> 0.08
A13: I | B13: COFINS | C13: 0.03
B14: PIS | C14: 0.0065
B15: ISS | C15: 0.03 | E15: ISS
B16: CRPB ( 0% ou 3,6% - Desoneração) | C16: 0
A17: TOTAL BDI 1 - OBRAS E SERVIÇOS | C17: =ROUND(((1+C8+C9+C10)*(1+C11)*(1+C12)/(1-C13-C14-C15-C16))-1,4) -> 0.2449
A19: C0MPOSIÇÃO DO BDI 2 - FORNECIMENTO DE MATERIAIS E EQUIPAMENTOS
A20: CONSTRUÇÃO DE REDES DE ABASTECIMENTO DE ÁGUA, COLETA DE ESGOTO E CONSTRUÇÕES CORRELATAS
A21: SIGLA | B21: DISCRIMINAÇÃO DAS PARCELAS | C21: BDI - SEM DESONERAÇÃO
A22: AC | B22: Administração Central | C22: {=_xlfn.IFS($F$1<=150000,0.035,$F$1<=1500000,0.025,$F$1>1500000,0.01)} -> 0.025
A23: SG | B23: Seguro e Garantia | C23: {=_xlfn.IFS($F$1<=150000,0.008,$F$1<=1500000,0.005,$F$1>1500000,0.003)} -> 0.005
A24: R | B24: Risco | C24: {=_xlfn.IFS($F$1<=150000,0.009,$F$1<=1500000,0.008,$F$1>1500000,0.0055)} -> 0.008
A25: DF | B25: Despesas Financeiras | C25: {=_xlfn.IFS($F$1<=150000,0.011,$F$1<=1500000,0.0085,$F$1>1500000,0.0085)} -> 0.0085
A26: L | B26: Lucro | C26: {=_xlfn.IFS($F$1<=150000,0.05,$F$1<=1500000,0.04,$F$1>1500000,0.03)} -> 0.04
A27: I | B27: COFINS | C27: 0.03
B28: PIS | C28: 0.0065
B29: ISS | C29: 0
B30: CRPB ( 0% ou 3,6% - Desoneração) | C30: 0
A31: TOTAL BDI 2 - FORNECIMENTO DE MATERIAIS E EQUIPAMENTOS | C31: =ROUND(((1+C22+C23+C24)*(1+C25)*(1+C26)/(1-C27-C28-C29-C30))-1,4) -> 0.1299
A33: NOTA: 1) Alíquotas do PIS e COFINS definidas pelo Decreto nº 4.524/2002. 2) Alíquota do Imposto Sobre Serviço (ISS) definida pela da Lei Municipal nº 691/1984 alterada pela Lei 1.513 de 27/12/1989 - Art. 1°. 3) Alíquota da Contribuição Previdenciária sobre Receita Bruta (CPRB) definida pela Lei 13.161/2015. Aplicado apenas a desoneração. 4) Parâmetros de cálculo do BDI, estão conforme limites do Acórdão nº 2.622/2014 - TCU Plenário (TC 036.076/2011-2)

Sheet Memorial
B2: Tapume | D2: 2 Lados | F2: Escavação poço | O2: Escavação PV
B3: Comp. | C3: =3.1+1.4+1.7+1.4+0.25+0.5+0.15 -> 8.5 | D3: =C3*2 -> 17 | F3: Comp. | G3: =3.1+1.4 -> 4.5 | O3: Comp. | P3: 2
B4: Larg. | C4: =2+0.5+0.5 -> 3 | D4: =C4*2 -> 6 | F4: Larg. | G4: 3 | O4: Larg. | P4: 2
D5: =D3+D4 -> 23 | F5: Prof. | G5: =0.25+2.4+0.5+0.2+0.05 -> 3.4 | O5: Prof. | P5: =0.2+2.05+0.31+0.25+0.05 -> 2.86
G6: =G3*G4*G5 -> 45.9 | P6: =P3*P4*P5 -> 11.44
B7: Locação
B8: Comp. | C8: =C3 -> 8.5 | F8: Pavimento - Concreto
B9: Larg. | C9: =C4 -> 3 | F9: Comp. | G9: =0.15+0.5+0.25+1.4+1.7+1.4+3.1 -> 8.5 | Q9: Poço | T9: PV | W9: BASE ABRIGO
C10: =C8*C9 -> 25.5 | F10: Larg. | G10: =2+1 -> 3 | Q10: Forma | R10: =62.76-U10-X10 -> 49.72 | T10: Forma | U10: 12 | W10: Forma | X10: 1.04
B11: LR | F11: 0.05 | G11: =G9*G10 -> 25.5 | Q11: Aço | R11: 816.92 | T11: Aço | U11: 37.26 | W11: Aço | X11: 28.96
B12: Comp. | C12: 340 | F12: Recomposição | G12: =G11*F11 -> 1.275 | Q12: Concreto 40MPa | R12: =10.88-U12-X12 -> 9.73 | T12: Concreto 40MPa | U12: 0.81 | W12: Concreto 40MPa | X12: 0.34
B13: Larg. | C13: 1 | Q13: Concreto magro | R13: 0.52 | W13: Impermeabilização | X13: =1.4*1.2+((1.4*0.2)*2)+((1.2*0.2)*2) -> 2.72
F14: Piso abrigo elétrico | J14: Impermeabilização Poço bomba | M14: Impermeabilização PV
C15: =C10+C14 -> 25.5 | F15: Comp. | G15: 1.5 | J15: Alt. | K15: Larg. | M15: Area de parede poço | N15: A=Pi x D x H
F16: Larg. | G16: 0.3 | J16: =2.9+0.75 -> 3.65 | K16: =3.1-0.25-0.25 -> 2.6 | L16: =J16*K16 -> 9.49 | N16: =PI()*1.04*(0.05+0.25+0.31+2.05+0.2) -> 9.3443532
G17: =G15*G16 -> 0.45 | J17: =2.4+0.5 -> 2.9 | K17: =2-0.25-0.25 -> 1.5 | L17: =J17*K17 -> 4.35
L18: =L16+L17 -> 13.84
L19: =(L18*2)+L22 -> 40.08
B20: Mureta energia | J20: Impermeabilização tampa Poço
B21: Comp | C21: 0.5 | J21: Comp. | K21: Larg.
B22: Alt | C22: 1.8 | J22: 3.1 | K22: 2 | L22: =(J22*K22)*2 -> 12.4
C23: =C21*C22 -> 0.9
B25: Pintura mureta
B26: =C23*2 -> 1.8 | C26: =(C22*0.22)*2 -> 0.792
C27: =B26+C26 -> 2.592

Sheet Quantitativo
A1: QUANTITATIVO
A2: ITEM | B2: DESCRIÇÃO | C2: QUANTIDADE | D2: UNIDADE
A3: 1 | B3: TUBO POLIETILENO PE 100 PN10 FAIXA OCRE PARA ESGOTO (BARRA COM 6,0 M) DE160 - L=1600 mm | C3: 1 | D3: UN
A4: 2 | B4: COLARINHO POLIETILENO INJETADO TERMOFUSAO PE 100 PN10 DE160 | C4: 1 | D4: UN
A5: 3 | B5: VALVULA GUILHOTINA BIDIRECIONAL FD LUG/SEMILUG/WAFER MANUAL CASTELO QUADRADO E VOLANTE PARA ESGOTO/AGUA BRUTA 16 BAR FURACAO PN16 DN80 | C5: 1 | D5: UN
A6: 4 | B6: TOCO DE TUBO FD FF PN10 MEDINDO 0.25M PARA ESGOTO DN150 | C6: 1 | D6: UN
A7: 5 | B7: CONJUNTO MOTOBOMBA EM LINHA (Q=3,5l/s; H=9,97mca) | C7: 1 | D7: CJ
A8: 6 | B8: TE REDUCAO FD FFF PARA ESGOTO PN16 DN100 DN80 | C8: 1 | D8: UN
A9: 7 | B9: VENTOSA COMBINADA/TRIPLICE FUNCAO PARA ESGOTO CORPO EM PRFV OU NYLON REFORCADO COM CAPACIDADE VAZAO MINIMA A 0,4 BAR DE 220,0 M3/H FLANGE PN10/16 DN100 POL4" | C9: 1 | D9: UN
A10: 8 | B10: TE FD FFF PN16 PARA ESGOTO DN80 | C10: 1 | D10: UN
A11: 9 | B11: TOCO DE TUBO FD FF PN16 MEDINDO 0.50 METROS PARA ESGOTO DN80 | C11: 1 | D11: UN | F11: 0.5
A12: 10 | B12: TOCO DE TUBO FD FF 700MM COM ABA DE VEDACAO PN16 PARA ESGOTO DN80 | C12: 1 | D12: UN | F12: 0.7
A13: 11 | B13: COLARINHO POLIETILENO INJETADO TERMOFUSAO PE 100 PN10 DE90 | C13: 1 | D13: UN
A14: 12 | B14: TUBO FD K9 FF (SOLDA INTERFERENCIA) PARA ESGOTO PN16 MEDINDO 1,20M DN80 | C14: 1 | D14: UN | F14: 1.2
A15: 13 | B15: EXTREMIDADE FD PF 700MM COM ABA DE VEDACAO PARA ESGOTO PN16 DN80 | C15: 1 | D15: UN | F15: 0.7
A16: 14 | B16: CURVA FD JE 2GS BB 22 PARA ESGOTO DN80 | C16: 1 | D16: UN
A17: 15 | B17: TUBO FD K9 PP PARA ESGOTO (0,9M) DN80 | C17: 1 | D17: UN | F17: 0.9
A18: 16 | B18: CONJUNTO MOTOBOMBA SUBMERSIVEL Q=22,9 M3/H (DRENAGEM) | C18: 1 | D18: UN | F18: =F11+F12+F14+F15+F17 -> 4
A19: 17 | B19: ADAPTADOR CURTO PPR80 BOLSA/ROSCA MACHO BSP TERMOFUSAO PN 10 DE 90 POL 3" | C19: 1 | D19: UN
A20: 18 | B20: TUBO PPR80 JS PP TERMOFUSAO (BARRA COM 6,0 METROS) PN 10 DE 90 | C20: 1 | D20: UN
A21: 19 | B21: UNIAO PPR FLANGEADA DE90 PN10 | C21: 1 | D21: UN
A22: 20 | B22: CURVA LONGA 90 POLIPROPILENO RANDOMICO (PPR) DE90 | C22: 1 | D22: UN
A23: s/n | B23: FLANGE ACO CARBONO PARA COLARINHO PEAD EPOXI ISO 12944 320UM C5M DURABILIDADE ALTA OU PP (NBR 7675/15593) PN10 DE160 DN150 | C23: 1 | D23: CJ
A24: s/n | B24: FLANGE ACO CARBONO PARA COLARINHO PEAD EPOXI ISO 12944 320UM C5M DURABILIDADE ALTA OU PP (NBR 7675/15593) PN16 DE90 DN80 | C24: 1 | D24: CJ
A25: s/n | B25: KIT PARAFUSO PORCA ARRUELA LISA ACO CARBONO ARRUELA VEDACAO FURACAO PARA ESGOTO PN10 NBR 7675 PARA FLANGE AVULSA PARA COLARINHO PEAD DN150 | C25: 1 | D25: CJ
A26: s/n | B26: KIT PARAFUSO PORCA ARRUELA LISA ACO CARBONO ARRUELA VEDACAO FURACAO PARA ESGOTO PN16 NBR 7675 PARA FLANGE AVULSA PARA COLARINHO PEAD DN80 | C26: 1 | D26: CJ
A27: s/n | B27: KIT PARAFUSO PORCA ARRUELA LISA ACO CARBONO ARRUELA VEDACAO FURACAO PN16 NBR 7675 DN80 | C27: 4 | D27: CJ
A28: s/n | B28: KIT PARAFUSO PORCA ARRUELA LISA ACO CARBONO ARRUELA VEDACAO FURACAO PN16 NBR 7675 DN100 | C28: 2 | D28: CJ
A29: s/n | B29: KIT PARAFUSO PORCA ARRUELA LISA ACO CARBONO ARRUELA VEDACAO FURACAO PARA ESGOTO PN16 PARA VALVULAS BORBOLETA WAFER AWWA C504 NBR 7675 DN80 | C29: 1 | D29: CJ
A30: s/n | B30: KIT PARAFUSO PORCA ARRUELA LISA ACO INOX ARRUELA VEDACAO FURACAO PARA ESGOTO PN10 NBR 7675 DN150 | C30: 1 | D30: CJ
B31: ABRIGO METÁLICO | E31: https://loja.bsepaineis.com.br/armarios-paineis-modulares/painel-modular-padrao/de-2200-100mm-de-altura/painel-eletrico-modular-2200-100x800x800?nocache=1782147986842
B34: CABO DE COBRE, TÊMPERA MOLE, CLASSE 5, 0,6/1KV, EPR 90º, PP TETRAPOLAR EPROTENAX GSETTE - COR PRETA 2,5MM²
B36: =LOWER(B34) -> cabo de cobre, têmpera mole, classe 5, 0,6/1kv, epr 90º, pp tetrapolar eprotenax gsette - cor preta 2,5mm²

Sheet Preços tubos e conexões
B2: Descrição | L2: Valor | M2: Valor Total
B3: TUBO TB PE100 PLO 160 PN16 SDR11 M.FG | K3: 1 | L3: 180.61 | M3: 180.61
B4: COLARINHO DE160 PN16 SDR11 M.GF | K4: 1 | L4: 117.81 | M4: 117.81
B5: TOCO TOF10/16 150 X 250 MM M.PA | K5: 1 | L5: 712.96 | M5: 712.96
B6: TE-FLS TFF10/16 100 X 80 MM M.PA | K6: 1 | L6: 666.2 | M6: 666.2
B7: TE-FLS TFF10/16/25 80 X 80 MM M.PA | K7: 1 | L7: 579.82 | M7: 579.82
B8: TUBO-FLS TFL10/16/25 80 X 700 MM AV | K8: 1 | L8: 1679.95 | M8: 1679.95
B9: COLARINHO DE 90 PN16 SDR11 M.AG | K9: 1 | L9: 71.39 | M9: 71.39
B10: TUBO-PTA-PTA TUBINTCL 150 X 1260 MM | K10: 1 | L10: 1308.15 | M10: 1308.15
B11: TUBO-FLS TFL10/16/25 80 X 700 MM AV | K11: 1 | L11: 1679.95 | M11: 1679.95
B12: CURVA-FLS C22FF10/16/25 80 MM M.PA | K12: 1 | L12: 338 | M12: 338
B13: TUBO-PTA-PTA TUBINTCL 80 X 700 MM | K13: 1 | L13: 586.74 | M13: 586.74
B14: COLARINHO DE160 PN16 SDR11 M.GF | K14: 1 | L14: 117.81 | M14: 117.81
... B58: TUBO-PTA-PTA TUBINTCL 150 X 1400 MM | K58: 1 | L58: 1173.41 | M58: 1173.41
E61: Cidade: SAO PAULO Fax: | I61: Site:
B62: I.E.: 115674165111 | J62: Vendedor: 63
G64: Bairro: | I64: ALPHAVILLE INDUSTRIA CEP: 06455000 | L64: Cidade:
A65: FAX: 00000000000 | H65: Contato: DENIO | K65: EMAIL: denio.maciel@2ssconstrucoes.com.br
B67: Descrição | J67: Unid. | M67: Valor Total
B68: TUBO-PTA-PTA TUBINTCL 150 X 1000 MM | J68: PC | M68: 935.48
B69: ARRUELA BOR. ABFNBR10 50 MM GB | J69: PC | M69: 8.56
B70: PARAF.PORC.AR G.FOGO 5/8 X 4 TP | J70: CJ | M70: 40.45
B71: ARRUELA BOR. ABFNBR10 80 MM GB | J71: PC | M71: 13.32
B72: PARAF.PORC.AR G.FOGO 5/8 X 4 TP | J72: CJ | M72: 80.9
B73: ARRUELA BOR. ABFNBR10 150 MM GB | J73: PC | M73: 25.2
B74: PARAF.PORC.AR G.FOGO ¾ X 4.½ TP | J74: CJ | M74: 128
D75: 2024.47
F80: FOB: 
C81: 10 dias A COMBINAR- sujeito à análise de INCLUSOS até 0 dias

Sheet Elétrico
A2: Item | D2: Descrição | I2: Unid. | L2: Quant. | O2: Valor
A3: 1 | D3: IMPLANTAÇÃO GERAL
A4: 1.01 | D4: ELETRODUTO/DUTO PEAD FLEXIVEL PAREDE SIMPLES, CORRUGACAO HELICOIDAL, COR PRETA, SEM ROSCA, DE 2", PARA CABEAMENTO SUBTERRANEO (NBR 15715) | I4: M | L4: 6
A5: 1.02 | D5: ELETRODUTO Ø 2" ACO CARBONO GALVANIZADO ZICAGEM POR IMERSAO A ǪUENTE, SEM ROSCA, CL PESADA (PAREDE 2,25MM), NBR 5598. BARRA DE 3,0 M-FORNECIMENTO E ASS | I5: M | L5: 12
A6: 1.03 | D6: CONDULETE TIPO LB DE ALUMÍNIO, TAMPA CEGA, Ø 2" | I6: UN. | L6: 7
A7: 1.04 | D7: CONDULETE TIPO T DE ALUMÍNIO, TAMPA CEGA, Ø 2" | I7: UN. | L7: 1
A8: 1.05 | D8: CAIXA DE CONCRETO ARMADO PRE-MOLDADO, COM FUNDO E TAMPA, DIMENSOES DE 0,40 X 0,40 X 0,40 M | I8: UN. | L8: 1
A9: 2 | D9: RELAÇÃO DE EQUIPAMENTOS ELÉTRICOS E DE AUTOMAÇÃO
A10: 2.02 | D10: PAINEL ELÉTRICO ǪCM - ǪUADRO DE COMANDO E PROTEÇÃO DE MOTORES, COM ACIONAMENTO PARA 2 MOTOR COM INVERSOR 3CV, 220V, 3F, 60HZ, INSTALAÇÃO ABRIGADA, A SER MONTADO E TESTADO CONFORME PROJETO E ESPECIFICAÇÃO TÉCNICA. | I10: UN. | L10: 1
A11: 2.03 | D11: CHAVE DE NÍVEL TIPO PERA COM CONTATO NA+NF | I11: UN. | L11: 1
A12: 3 | D12: RELAÇÃO DE SERVIÇOS ESPECÍFICOS E DE AUTOMAÇÃO
A13: 3.01 | D13: ELETRICISTA (HORISTA) | I13: H | L13: 528
A14: 3.02 | D14: AJUDANTE DE ELETRICISTA (HORISTA) | I14: H | L14: 528
A15: 3.03 | D15: PEDREIRO (HORISTA) | I15: H | L15: 176
A16: 3.04 | D16: AUXILIAR DE PEDREIRO (HORISTA) | I16: H | L16: 176
A17: 3.05 | D17: COMISSIONAMENTO E STARTUP DE ELEVATORIA COM 2 CMB (1+1) COM CLP | I17: H | L17: 80
A18: 4 | D18: IMPLANTAÇÃO ATERRAMENTO GERAL
A19: 4.01 | D19: CABO DE COBRE NU 50MM² - 7 FIOS X DN 3,00MM | I19: M | L19: 20
A20: 4.02 | D20: CAIXA DE EǪUIPOTENCIALIZAÇÃO EM TERMOPLÁSTICO COM 9 FUROS | I20: UN | L20: 1
A21: 4.03 | D21: HASTE DE ATERRAMENTO DIÂMETRO 3/4" COMPRIMENTO 3,00M | I21: UN | L21: 4 | O21: 5 | P21: =3*4 -> 12
A22: 4.04 | D22: TERMINAL ESTANHADO 1 FURO A COMPRESSÃO, REF: TEL-5150 | I22: UN | L22: 5 | P22: =2.4*5 -> 12
A23: 4.05 | D23: CONECTORES DE PRESSÃO TIPO SPLIT-BOLT, REF: TEL-5018 | I23: UN | L23: 5
A24: 4.06 | D24: CAIXA DE INSPEÇÃO EM PROPILENO DN 300MM TEL-552PP | I24: UN | L24: 1
A25: 5 | D25: LISTA DE CABOS GERAIS
A26: 5.01 | D26: CABO DE COBRE, TÊMPERA MOLE, CLASSE 5, 0,6/1KV, EPR 90º, UNIPOLAR TIPO EPROTENAX GSETTE - COR PRETA 10MM² | I26: M | L26: 36
A27: 5.02 | D27: CABO DE COBRE, TÊMPERA MOLE, CLASSE 5, 0,6/1KV, EPR 90º, UNIPOLAR TIPO EPROTENAX GSETTE - COR AZUL 10MM² | I27: M | L27: 12
A28: 5.03 | D28: CABO DE COBRE, TÊMPERA MOLE, CLASSE 5, 0,6/1KV, EPR 90º, UNIPOLAR TIPO EPROTENAX GSETTE - COR VERDE 10MM² | I28: M | L28: 12
A29: 5.04 | D29: CABO DE COBRE, TÊMPERA MOLE, CLASSE 5, 0,6/1KV, EPR 90º, PP TETRAPOLAR EPROTENAX GSETTE - COR PRETA 2,5MM² | I29: M | L29: 30
A30: 5.05 | D30: CABO DE INSTRUMENTAÇÃO COM BLINDAGEM ELETROSTÁTICA 1X[2#1,5MM²+SH] | I30: M | L30: 10
D32: CABO DE COBRE, TÊMPERA MOLE, CLASSE 5, 0,6/1KV, EPR 90º, UNIPOLAR TIPO EPROTENAX GSETTE - COR PRETA 10MM² | I32: M | L32: 36
D33: CABO DE COBRE, TÊMPERA MOLE, CLASSE 5, 0,6/1KV, EPR 90º, UNIPOLAR TIPO EPROTENAX GSETTE - COR AZUL 10MM² | I33: M | L33: 12
D34: CABO DE COBRE, TÊMPERA MOLE, CLASSE 5, 0,6/1KV, EPR 90º, UNIPOLAR TIPO EPROTENAX GSETTE - COR VERDE 10MM² | I34: M | L34: 12
D35: CABO DE COBRE, TÊMPERA MOLE, CLASSE 5, 0,6/1KV, EPR 90º, PP TETRAPOLAR EPROTENAX GSETTE - COR PRETA 2,5MM² | I35: M | L35: 30
D36: CABO DE INSTRUMENTAÇÃO COM BLINDAGEM ELETROSTÁTICA 1X[2#1,5MM²+SH] | I36: M | L36: 10

Sheet ORÇAMENTO SINTÉTICO - PA4
B1: ORÇAMENTO SINTÉTICO SEM DESONERAÇÃO FONTE: SANEPAR
B3: #VALUE! | F3: ELABORAÇÃO DE ORÇAMENTO PARA ELEVATÓRIA PA4 | I3: CIDADE: | K3: UBIRATÃ | N3: #VALUE!
I4: ESTADO: | K4: PARANÁ
I5: SISTEMA:
I6: MICROBACIA / ÁREA: | K6: PA4
I7: DATA: | K7: 46147
I8: REVISÃO: | K8: R00
I9: ELABORAÇÃO: | K9: DANIEL GAMA
I10: ENG. RESPONSÁVEL: | K10: RODRIGO A. ZANATTA
I11: CREA: | K11: SC-0680240/D
B12: Código | E12: Descrição | G12: Tipo | H12: Origem | I12: Quant. | J12: Un. Med. | K12: Valor Unitário | M12: BDI | N12: Preço Unit. C/ BDI | O12: Custo Total | P12: Preço Total C/ BDI
E13: SERVIÇOS INICIAIS | P13: =P14+P21+P30 -> 14184.988
B14: 001 | E14: CANTEIRO DE OBRAS | P14: =P15+P17+P19 -> 2953.5901
B15: 001.003 | E15: ABASTECIMENTO DE ÁGUA | K15: =[2]REF_TAB_PREÇOS_SANEPAR!I27 | M15: =IF(G15="", "", IFERROR(IF(G15="Mat", [2]BDI!C$31, IF(G15="MO", [2]BDI!C$17)), "")) | P15: =P16 -> 244.84693
B16: 001003001 | E16: Entrada provisória de água | G16: MO | H16: Sanepar | I16: 1 | J16: ud | K16: =[2]REF_TAB_PREÇOS_SANEPAR!I28 -> 196.68 | M16: =IF(G16="", "", IFERROR(IF(G16="Mat", BDI!C$31, IF(G16="MO", BDI!C$17)), "")) -> 0.2449 | N16: =IF(K16="","",K16*(1+M16)) -> 244.84693 | O16: =K16*I16 -> 196.68 | P16: =N16*I16 -> 244.84693
B17: 001.004 | E17: PROTEÇÃO DA ÁREA | K17: =[2]REF_TAB_PREÇOS_SANEPAR!I32 | M17: =IF(G17="", "", IFERROR(IF(G17="Mat", BDI!C$31, IF(G17="MO", BDI!C$17)), "")) | P17: =P18 -> 210.94103
B18: 001004004 | E18: Tapume de chapas metálicas | G18: Mat | H18: Sanepar | I18: 1 | J18: m | K18: =[2]REF_TAB_PREÇOS_SANEPAR!I36 -> 186.69 | M18: =IF(G18="", "", IFERROR(IF(G18="Mat", BDI!C$31, IF(G18="MO", BDI!C$17)), "")) -> 0.1299 | N18: =IF(K18="","",K18*(1+M18)) -> 210.94103 | O18: =K18*I18 -> 186.69 | P18: =N18*I18 -> 210.94103
B19: 001.005 | E19: PLACA DE OBRA | K19: =[2]REF_TAB_PREÇOS_SANEPAR!I37 | M19: =IF(G19="", "", IFERROR(IF(G19="Mat", BDI!C$31, IF(G19="MO", BDI!C$17)), "")) | P19: =P20 -> 2497.8021
B20: 001005001 | E20: Em chapa metálica | G20: Mat | H20: Sanepar | I20: 4 | J20: m² | K20: =[2]REF_TAB_PREÇOS_SANEPAR!I38 -> 552.66 | M20: =IF(G20="", "", IFERROR(IF(G20="Mat", BDI!C$31, IF(G20="MO", BDI!C$17)), "")) -> 0.1299 | N20: =IF(K20="","",K20*(1+M20)) -> 624.45053 | O20: =K20*I20 -> 2210.64 | P20: =N20*I20 -> 2497.8021
B21: 002 | E21: SERVIÇOS TÉCNICOS | K21: =[2]REF_TAB_PREÇOS_SANEPAR!I39 | M21: =IF(G21="", "", IFERROR(IF(G21="Mat", BDI!C$31, IF(G21="MO", BDI!C$17)), "")) | P21: =P22+P26+P28 -> 9389.9446
B22: 002.001 | E22: TOPOGRAFIA E GEODÉSIA - SERVIÇOS | K22: =[2]REF_TAB_PREÇOS_SANEPAR!I40 | M22: =IF(G22="", "", IFERROR(IF(G22="Mat", BDI!C$31, IF(G22="MO", BDI!C$17)), "")) | P22: =P23+P24+P25 -> 150.45861
B23: 002001004 | E23: Locação de furos de sondagem | G23: MO | H23: Sanepar | I23: 3 | J23: ud | K23: =[2]REF_TAB_PREÇOS_SANEPAR!I44 -> 39.04 | M23: =IF(G23="", "", IFERROR(IF(G23="Mat", BDI!C$31, IF(G23="MO", BDI!C$17)), "")) -> 0.2449 | N23: =IF(K23="","",K23*(1+M23)) -> 48.600896 | O23: =K23*I23 -> 117.12 | P23: =N23*I23 -> 145.80269
B24: 002001008 | E24: Levantamento planialtimétrico cadastral de área: 0,00 m² < área < 1.000 m² | G24: MO | H24: Sanepar | I24: 1 | J24: m² | K24: =[2]REF_TAB_PREÇOS_SANEPAR!I48 -> 1.02 | M24: =IF(G24="", "", IFERROR(IF(G24="Mat", BDI!C$31, IF(G24="MO", BDI!C$17)), "")) -> 0.2449 | N24: =IF(K24="","",K24*(1+M24)) -> 1.269798 | O24: =K24*I24 -> 1.02 | P24: =N24*I24 -> 1.269798
B25: 002001043 | E25: Locação da obra com auxílio de equipamento topográfico | G25: MO | H25: Sanepar | I25: 1 | J25: m² | K25: =[2]REF_TAB_PREÇOS_SANEPAR!I83 -> 2.72 | M25: =IF(G25="", "", IFERROR(IF(G25="Mat", BDI!C$31, IF(G25="MO", BDI!C$17)), "")) -> 0.2449 | N25: =IF(K25="","",K25*(1+M25)) -> 3.386128 | O25: =K25*I25 -> 2.72 | P25: =N25*I25 -> 3.386128
B26: 002.004 | E26: SONDAGEM A PERCUSSÃO | K26: =[2]REF_TAB_PREÇOS_SANEPAR!I138 | M26: =IF(G26="", "", IFERROR(IF(G26="Mat", BDI!C$31, IF(G26="MO", BDI!C$17)), "")) | P26: =P27 -> 9047.622
B27: 002004002 | E27: Perfuração em solo (SPT) com estadia da equipe | G27: MO | H27: Sanepar | I27: 25 | J27: m | K27: =[2]REF_TAB_PREÇOS_SANEPAR!I140 -> 290.71 | M27: =IF(G27="", "", IFERROR(IF(G27="Mat", BDI!C$31, IF(G27="MO", BDI!C$17)), "")) -> 0.2449 | N27: =IF(K27="","",K27*(1+M27)) -> 361.90488 | O27: =K27*I27 -> 7267.75 | P27: =N27*I27 -> 9047.622
B28: 002.007 | E28: CADASTRO DE OBRAS | K28: =[2]REF_TAB_PREÇOS_SANEPAR!I167 | M28: =IF(G28="", "", IFERROR(IF(G28="Mat", BDI!C$31, IF(G28="MO", BDI!C$17)), "")) | P28: =P29 -> 191.86399
B29: 002007005 | E29: Cadastro de obra localizada "As Built" | G29: MO | H29: Sanepar | I29: 1 | J29: ud | K29: =[2]REF_TAB_PREÇOS_SANEPAR!I172 -> 154.12 | M29: =IF(G29="", "", IFERROR(IF(G29="Mat", BDI!C$31, IF(G29="MO", BDI!C$17)), "")) -> 0.2449 | N29: =IF(K29="","",K29*(1+M29)) -> 191.86399 | O29: =K29*I29 -> 154.12 | P29: =N29*I29 -> 191.86399
B30: 003 | E30: SERVIÇOS PRELIMINARES | K30: =[2]REF_TAB_PREÇOS_SANEPAR!I173 | M30: =IF(G30="", "", IFERROR(IF(G30="Mat", BDI!C$31, IF(G30="MO", BDI!C$17)), "")) | P30: =P31+P33+P36 -> 1841.4532
B31: 003.002 | E31: ACESSO PROVISÓRIO | K31: =[2]REF_TAB_PREÇOS_SANEPAR!I184 | M31: =IF(G31="", "", IFERROR(IF(G31="Mat", BDI!C$31, IF(G31="MO", BDI!C$17)), "")) | P31: =P32 -> 37.658225
B32: 003002001 | E32: Acesso provisório | G32: MO | H32: Sanepar | I32: 5 | J32: m² | K32: =[2]REF_TAB_PREÇOS_SANEPAR!I185 -> 6.05 | M32: =IF(G32="", "", IFERROR(IF(G32="Mat", BDI!C$31, IF(G32="MO", BDI!C$17)), "")) -> 0.2449 | N32: =IF(K32="","",K32*(1+M32)) -> 7.531645 | O32: =K32*I32 -> 30.25 | P32: =N32*I32 -> 37.658225
B33: 003.005 | E33: SINALIZAÇÃO DE SEGURANÇA | K33: =[2]REF_TAB_PREÇOS_SANEPAR!I201 | M33: =IF(G33="", "", IFERROR(IF(G33="Mat", BDI!C$31, IF(G33="MO", BDI!C$17)), "")) | P33: =P34+P35 -> 2.417986
B34: 003005001 | E34: Fita plástica | G34: Mat | H34: Sanepar | I34: 1 | J34: m | K34: =[2]REF_TAB_PREÇOS_SANEPAR!I202 -> 0.3 | M34: =IF(G34="", "", IFERROR(IF(G34="Mat", BDI!C$31, IF(G34="MO", BDI!C$17)), "")) -> 0.1299 | N34: =IF(K34="","",K34*(1+M34)) -> 0.33897 | O34: =K34*I34 -> 0.3 | P34: =N34*I34 -> 0.33897
B35: 003005004 | E35: Tapume em tela plástica | G35: Mat | H35: Sanepar | I35: 1 | J35: m | K35: =[2]REF_TAB_PREÇOS_SANEPAR!I205 -> 1.84 | M35: =IF(G35="", "", IFERROR(IF(G35="Mat", BDI!C$31, IF(G35="MO", BDI!C$17)), "")) -> 0.1299 | N35: =IF(K35="","",K35*(1+M35)) -> 2.079016 | O35: =K35*I35 -> 1.84 | P35: =N35*I35 -> 2.079016
B36: 003.006 | E36: SINALIZAÇÃO DE TRÂNSITO | K36: =[2]REF_TAB_PREÇOS_SANEPAR!I206 | M36: =IF(G36="", "", IFERROR(IF(G36="Mat", BDI!C$31, IF(G36="MO", BDI!C$17)), "")) | P36: =P37+P38 -> 1801.377
B37: 003006001 | E37: Placa de advertência 1,00 x 1,00 m | G37: Mat | H37: Sanepar | I37: 4 | J37: ud | K37: =[2]REF_TAB_PREÇOS_SANEPAR!I207 -> 151.33 | M37: =IF(G37="", "", IFERROR(IF(G37="Mat", BDI!C$31, IF(G37="MO", BDI!C$17)), "")) -> 0.1299 | N37: =IF(K37="","",K37*(1+M37)) -> 170.98777 | O37: =K37*I37 -> 605.32 | P37: =N37*I37 -> 683.95107
B38: 003006002 | E38: Placa de advertência 1,00 x 2,00 m | G38: Mat | H38: Sanepar | I38: 4 | J38: ud | K38: =[2]REF_TAB_PREÇOS_SANEPAR!I208 -> 247.24 | M38: =IF(G38="", "", IFERROR(IF(G38="Mat", BDI!C$31, IF(G38="MO", BDI!C$17)), "")) -> 0.1299 | N38: =IF(K38="","",K38*(1+M38)) -> 279.35648 | O38: =K38*I38 -> 988.96 | P38: =N38*I38 -> 1117.4259
E39: POÇO DE SUCÇÃO E RAC | M39: =IF(G39="", "", IFERROR(IF(G39="Mat", BDI!C$31, IF(G39="MO", BDI!C$17)), "")) | P39: =P40+P45+P59+P68+P131 -> 209763.42
B40: 004 | E40: MOVIMENTO DE SOLOS | K40: =[2]REF_TAB_PREÇOS_SANEPAR!I249 | M40: =IF(G40="", "", IFERROR(IF(G40="Mat", BDI!C$31, IF(G40="MO", BDI!C$17)), "")) | P40: =P41+P43 -> 34.135158
B41: 004.007 | E41: ESCAVAÇÃO MECÂNICA, NÃO EM VALAS, EM QUALQUER TIPO DE SOLO, EXCETO ROCHA | K41: =[2]REF_TAB_PREÇOS_SANEPAR!I296 | M41: =IF(G41="", "", IFERROR(IF(G41="Mat", BDI!C$31, IF(G41="MO", BDI!C$17)), "")) | P41: =P42 -> 22.955956
B42: 004007003 | E42: Solos em geral, profundidade 0 m < h = 6 m | G42: MO | H42: Sanepar | I42: 1 | J42: m³ | K42: =[2]REF_TAB_PREÇOS_SANEPAR!I299 -> 18.44 | M42: =IF(G42="", "", IFERROR(IF(G42="Mat", BDI!C$31, IF(G42="MO", BDI!C$17)), "")) -> 0.2449 | N42: =IF(K42="","",K42*(1+M42)) -> 22.955956 | O42: =K42*I42 -> 18.44 | P42: =N42*I42 -> 22.955956
B43: 004.015 | E43: COMPACTAÇÃO NÃO EM VALAS | K43: =[2]REF_TAB_PREÇOS_SANEPAR!I330 | M43: =IF(G43="", "", IFERROR(IF(G43="Mat", BDI!C$31, IF(G43="MO", BDI!C$17)), "")) | P43: =P44 -> 11.179202
B44: 004015001 | E44: Sem controle do GC | G44: MO | H44: Sanepar | I44: 1 | J44: m³ | K44: =[2]REF_TAB_PREÇOS_SANEPAR!I331 -> 8.98 | M44: =IF(G44="", "", IFERROR(IF(G44="Mat", BDI!C$31, IF(G44="MO", BDI!C$17)), "")) -> 0.2449 | N44: =IF(K44="","",K44*(1+M44)) -> 11.179202 | O44: =K44*I44 -> 8.98 | P44: =N44*I44 -> 11.179202
B45: 008 | E45: FUNDAÇÕES E ESTRUTURA | M45: =IF(G45="", "", IFERROR(IF(G45="Mat", BDI!C$31, IF(G45="MO", BDI!C$17)), "")) | P45: =P46+P48+P51+P53+P55+P57 -> 2267.3488
B46: 008.009 | E46: FÔRMA PARA VIGA, PILAR E PAREDE | M46: =IF(G46="", "", IFERROR(IF(G46="Mat", BDI!C$31, IF(G46="MO", BDI!C$17)), "")) | P46: =P47 -> 151.30515
B47: 008009008 | E47: Plana em chapa resinada e= 18 mm | G47: MO | H47: Sanepar | I47: 1 | J47: m² | K47: 121.54 | M47: =IF(G47="", "", IFERROR(IF(G47="Mat", BDI!C$31, IF(G47="MO", BDI!C$17)), "")) -> 0.2449 | N47: =IF(K47="","",K47*(1+M47)) -> 151.30515 | O47: =K47*I47 -> 121.54 | P47: =N47*I47 -> 151.30515
B48: 008.019 | E48: ARMADURA | M48: =IF(G48="", "", IFERROR(IF(G48="Mat", BDI!C$31, IF(G48="MO", BDI!C$17)), "")) | N48: =IF(K48="","",K48*(1+M48)) | P48: =P49+P50 -> 39.139656
B49: 008019001 | E49: Em aço CA-50 | G49: MO | H49: Sanepar | I49: 1 | J49: kg | K49: 15.36 | M49: =IF(G49="", "", IFERROR(IF(G49="Mat", BDI!C$31, IF(G49="MO", BDI!C$17)), "")) -> 0.2449 | N49: =IF(K49="","",K49*(1+M49)) -> 19.121664 | O49: =K49*I49 -> 15.36 | P49: =N49*I49 -> 19.121664
B50: 008019002 | E50: Em aço CA-60 | G50: MO | H50: Sanepar | I50: 1 | J50: kg | K50: 16.08 | M50: =IF(G50="", "", IFERROR(IF(G50="Mat", BDI!C$31, IF(G50="MO", BDI!C$17)), "")) -> 0.2449 | N50: =IF(K50="","",K50*(1+M50)) -> 20.017992 | O50: =K50*I50 -> 16.08 | P50: =N50*I50 -> 20.017992
B51: 008.021 | E51: CONCRETO CONVENCIONAL | M51: =IF(G51="", "", IFERROR(IF(G51="Mat", BDI!C$31, IF(G51="MO", BDI!C$17)), "")) | P51: =P52 -> 1012.9876
B52: 008021002 | E52: fck = 15,0 MPa | G52: MO | H52: Sanepar | I52: 1 | J52: m³ | K52: 813.71 | M52: =IF(G52="", "", IFERROR(IF(G52="Mat", BDI!C$31, IF(G52="MO", BDI!C$17)), "")) -> 0.2449 | N52: =IF(K52="","",K52*(1+M52)) -> 1012.9876 | O52: =K52*I52 -> 813.71 | P52: =N52*I52 -> 1012.9876
B53: 008.022 | E53: CONCRETO USINADO | M53: =IF(G53="", "", IFERROR(IF(G53="Mat", BDI!C$31, IF(G53="MO", BDI!C$17)), "")) | P53: =P54 -> 717.43587
B54: 008022020 | E54: fck = 40,0 MPa - slump 8 | G54: MO | H54: Sanepar | I54: 1 | J54: m³ | K54: 576.3 | M54: =IF(G54="", "", IFERROR(IF(G54="Mat", BDI!C$31, IF(G54="MO", BDI!C$17)), "")) -> 0.2449 | N54: =IF(K54="","",K54*(1+M54)) -> 717.43587 | O54: =K54*I54 -> 576.3 | P54: =N54*I54 -> 717.43587
B55: 008.023 | E55: BOMBEAMENTO DE CONCRETO | M55: =IF(G55="", "", IFERROR(IF(G55="Mat", BDI!C$31, IF(G55="MO", BDI!C$17)), "")) | P55: =P56 -> 65.693373
B56: 008023001 | E56: Bombeamento de concreto usinado | G56: MO | H56: Sanepar | I56: 1 | J56: m³ | K56: 52.77 | M56: =IF(G56="", "", IFERROR(IF(G56="Mat", BDI!C$31, IF(G56="MO", BDI!C$17)), "")) -> 0.2449 | N56: =IF(K56="","",K56*(1+M56)) -> 65.693373 | O56: =K56*I56 -> 52.77 | P56: =N56*I56 -> 65.693373
B57: 008.030 | E57: PROTEÇÃO E IMPERMEABILIZAÇÃO DAS ESTRUTURAS DE CONCRETO | M57: =IF(G57="", "", IFERROR(IF(G57="Mat", BDI!C$31, IF(G57="MO", BDI!C$17)), "")) | P57: =P58 -> 280.78719
B58: 008030002 | E58: Impermeabilização flexível com poliuretano | G58: MO | H58: Sanepar | I58: 1 | J58: m² | K58: 225.55 | M58: =IF(G58="", "", IFERROR(IF(G58="Mat", BDI!C$31, IF(G58="MO", BDI!C$17)), "")) -> 0.2449 | N58: =IF(K58="","",K58*(1+M58)) -> 280.78719 | O58: =K58*I58 -> 225.55 | P58: =N58*I58 -> 280.78719
B59: 009 | E59: ASSENTAMENTOS | K59: =[2]REF_TAB_PREÇOS_SANEPAR!I673 | M59: =IF(G59="", "", IFERROR(IF(G59="Mat", BDI!C$31, IF(G59="MO", BDI!C$17)), "")) | P59: =P60+P62+P65 -> 6372.7499
B60: 009.002 | E60: TUBULAÇÃO DE PVC JE / JEI PARA ESGOTO | K60: =[2]REF_TAB_PREÇOS_SANEPAR!I689 | M60: =IF(G60="", "", IFERROR(IF(G60="Mat", BDI!C$31, IF(G60="MO", BDI!C$17)), "")) | P60: =P61 -> 13.432471
B61: 009002003 | E61: DN 200 | G61: MO | H61: Sanepar | I61: 1 | J61: m | K61: =[2]REF_TAB_PREÇOS_SANEPAR!I692 -> 10.79 | M61: =IF(G61="", "", IFERROR(IF(G61="Mat", BDI!C$31, IF(G61="MO", BDI!C$17)), "")) -> 0.2449 | N61: =IF(K61="","",K61*(1+M61)) -> 13.432471 | O61: =K61*I61 -> 10.79 | P61: =N61*I61 -> 13.432471
B62: 009.007 | E62: TUBULAÇÃO DE FERRO DÚCTIL JE/JE2GS/JTI | K62: =[2]REF_TAB_PREÇOS_SANEPAR!I763 | M62: =IF(G62="", "", IFERROR(IF(G62="Mat", BDI!C$31, IF(G62="MO", BDI!C$17)), "")) | P62: =P63+P64 -> 39.575371
B63: 009007003 | E63: DN 150 | G63: MO | H63: Sanepar | I63: 1 | J63: m | K63: =[2]REF_TAB_PREÇOS_SANEPAR!I766 -> 13.94 | M63: =IF(G63="", "", IFERROR(IF(G63="Mat", BDI!C$31, IF(G63="MO", BDI!C$17)), "")) -> 0.2449 | N63: =IF(K63="","",K63*(1+M63)) -> 17.353906 | O63: =K63*I63 -> 13.94 | P63: =N63*I63 -> 17.353906
B64: 009007004 | E64: DN 200 | G64: MO | H64: Sanepar | I64: 1 | J64: m | K64: =[2]REF_TAB_PREÇOS_SANEPAR!I767 -> 17.85 | M64: =IF(G64="", "", IFERROR(IF(G64="Mat", BDI!C$31, IF(G64="MO", BDI!C$17)), "")) -> 0.2449 | N64: =IF(K64="","",K64*(1+M64)) -> 22.221465 | O64: =K64*I64 -> 17.85 | P64: =N64*I64 -> 22.221465
B65: 009.018 | E65: POÇO DE VISITA TIPO D - DN 1200 | K65: =[2]REF_TAB_PREÇOS_SANEPAR!I841 | M65: =IF(G65="", "", IFERROR(IF(G65="Mat", BDI!C$31, IF(G65="MO", BDI!C$17)), "")) | P65: =P66+P67 -> 6319.7421
B66: 009018001 | E66: Para profundidade até 2,00 m | G66: MO | H66: Sanepar | I66: 1 | J66: ud | K66: =[2]REF_TAB_PREÇOS_SANEPAR!I842 -> 3473.34 | M66: =IF(G66="", "", IFERROR(IF(G66="Mat", BDI!C$31, IF(G66="MO", BDI!C$17)), "")) -> 0.2449 | N66: =IF(K66="","",K66*(1+M66)) -> 4323.961 | O66: =K66*I66 -> 3473.34 | P66: =N66*I66 -> 4323.961
B67: 009018002 | E67: Acréscimo para prof. superior a 2,00 m | G67: MO | H67: Sanepar | I67: =3.42-2 -> 1.42 | J67: m | K67: =[2]REF_TAB_PREÇOS_SANEPAR!I843 -> 1128.99 | M67: =IF(G67="", "", IFERROR(IF(G67="Mat", BDI!C$31, IF(G67="MO", BDI!C$17)), "")) -> 0.2449 | N67: =IF(K67="","",K67*(1+M67)) -> 1405.4797 | O67: =K67*I67 -> 1603.1658 | P67: =N67*I67 -> 1995.7811
B68: 014 | E68: INSTALAÇÕES DE PRODUÇÃO | M68: =IF(G68="", "", IFERROR(IF(G68="Mat", BDI!C$31, IF(G68="MO", BDI!C$17)), "")) | P68: =P69++P115+P117+P120+P122+P124+P126+P129 -> 200801.91
B69: 014.001 | E69: INSTALAÇÃO DE CONJUNTO MOTO BOMBA | K69: =[2]REF_TAB_PREÇOS_SANEPAR!I1330 | M69: =IF(G69="", "", IFERROR(IF(G69="Mat", BDI!C$31, IF(G69="MO", BDI!C$17)), "")) | P69: =SUM(P70:P114) -> 193768.21
B70: 019.002 | E70: Colarinho longo polietileno injetado ponta (para eletrofusao e termofusao) pe 100 pn 16 de 160 | G70: Mat | H70: CP | I70: 1 | J70: ud | K70: 329.648 | M70: =IF(G70="", "", IFERROR(IF(G70="Mat", BDI!C$31, IF(G70="MO", BDI!C$17)), "")) -> 0.1299 | N70: =IF(K70="","",K70*(1+M70)) -> 372.46928 | O70: =K70*I70 -> 329.648 | P70: =N70*I70 -> 372.46928
B71: 019.003 | E71: Tubo fd k9 ff (solda interferencia) para esgoto pn10 medindo 1,00m dn150 - l=708 mm | G71: Mat | H71: CP | I71: 1 | J71: ud | K71: 1 | M71: =IF(G71="", "", IFERROR(IF(G71="Mat", BDI!C$31, IF(G71="MO", BDI!C$17)), "")) -> 0.1299 | N71: =IF(K71="","",K71*(1+M71)) -> 1.1299 | O71: =K71*I71 -> 1 | P71: =N71*I71 -> 1.1299
B72: 019.004 | E72: Curva fd ff 45 para esgoto pn10 dn150 | G72: Mat | H72: CP | I72: 5 | J72: ud | K72: 1 | M72: =IF(G72="", "", IFERROR(IF(G72="Mat", BDI!C$31, IF(G72="MO", BDI!C$17)), "")) -> 0.1299 | N72: =IF(K72="","",K72*(1+M72)) -> 1.1299 | O72: =K72*I72 -> 5 | P72: =N72*I72 -> 5.6495
B73: 019.005 | E73: Te reducao fd fff para esgoto pn10 dn150 dn50 | G73: Mat | H73: CP | I73: 1 | J73: ud | K73: 1 | M73: =IF(G73="", "", IFERROR(IF(G73="Mat", BDI!C$31, IF(G73="MO", BDI!C$17)), "")) -> 0.1299 | N73: =IF(K73="","",K73*(1+M73)) -> 1.1299 | O73: =K73*I73 -> 1 | P73: =N73*I73 -> 1.1299
B74: 019.006 | E74: Junta de desmontagem travada aco/fd para esgoto pn10 dn150 | G74: Mat | H74: CP | I74: 1 | J74: ud | K74: 1 | M74: =IF(G74="", "", IFERROR(IF(G74="Mat", BDI!C$31, IF(G74="MO", BDI!C$17)), "")) -> 0.1299 | N74: =IF(K74="","",K74*(1+M74)) -> 1.1299 | O74: =K74*I74 -> 1 | P74: =N74*I74 -> 1.1299
B75: 019.007 | E75: Toco de tubo fd ff pn10 medindo 0,50 metros para esgoto dn150 | G75: Mat | H75: CP | I75: 1 | J75: ud | K75: 1 | M75: =IF(G75="", "", IFERROR(IF(G75="Mat", BDI!C$31, IF(G75="MO", BDI!C$17)), "")) -> 0.1299 | N75: =IF(K75="","",K75*(1+M75)) -> 1.1299 | O75: =K75*I75 -> 1 | P75: =N75*I75 -> 1.1299
B76: 019.008 | E76: Medidor de vazao eletromagnetico 1,0mpa alimentacao 24vcc sinal de saida modbus rtu para esgoto pn10 dn150 | G76: Mat | H76: CP | I76: 1 | J76: ud | K76: 12763.8 | M76: =IF(G76="", "", IFERROR(IF(G76="Mat", BDI!C$31, IF(G76="MO", BDI!C$17)), "")) -> 0.1299 | N76: =IF(K76="","",K76*(1+M76)) -> 14421.818 | O76: =K76*I76 -> 12763.8 | P76: =N76*I76 -> 14421.818
B77: 019.009 | E77: Tubo fd k9 ff (solda interferencia) para esgoto pn10 medindo 1,00m dn150 | G77: Mat | H77: CP | I77: 1 | J77: ud | K77: 1 | M77: =IF(G77="", "", IFERROR(IF(G77="Mat", BDI!C$31, IF(G77="MO", BDI!C$17)), "")) -> 0.1299 | N77: =IF(K77="","",K77*(1+M77)) -> 1.1299 | O77: =K77*I77 -> 1 | P77: =N77*I77 -> 1.1299
B78: 019.010 | E78: Junção fd fff para esgoto pn10 dn150 | G78: Mat | H78: CP | I78: 3 | J78: ud | K78: 1 | M78: =IF(G78="", "", IFERROR(IF(G78="Mat", BDI!C$31, IF(G78="MO", BDI!C$17)), "")) -> 0.1299 | N78: =IF(K78="","",K78*(1+M78)) -> 1.1299 | O78: =K78*I78 -> 3 | P78: =N78*I78 -> 3.3897
B79: 019.011 | E79: Toco de tubo fd ff pn10 medindo 0,50 metros para esgoto dn150 | G79: Mat | H79: CP | I79: 2 | J79: ud | K79: 1 | M79: =IF(G79="", "", IFERROR(IF(G79="Mat", BDI!C$31, IF(G79="MO", BDI!C$17)), "")) -> 0.1299 | N79: =IF(K79="","",K79*(1+M79)) -> 1.1299 | O79: =K79*I79 -> 2 | P79: =N79*I79 -> 2.2598
B80: 019.012 | E80: Valvula guilhotina bidirecional cf8m lug/semilug/wafer manual castelo quadrado e volante para esgoto 10bar furacao pn10 dn150 | G80: Mat | H80: CP | I80: 4 | J80: ud | K80: 2000.78 | M80: =IF(G80="", "", IFERROR(IF(G80="Mat", BDI!C$31, IF(G80="MO", BDI!C$17)), "")) -> 0.1299 | N80: =IF(K80="","",K80*(1+M80)) -> 2260.6813 | O80: =K80*I80 -> 8003.12 | P80: =N80*I80 -> 9042.7253
B81: 019.013 | E81: Tubo fd k9 ff (solda interferencia) para esgoto pn10 medindo 1,00m dn150 - l=666 mm | G81: Mat | H81: CP | I81: 2 | J81: ud | K81: 1 | M81: =IF(G81="", "", IFERROR(IF(G81="Mat", BDI!C$31, IF(G81="MO", BDI!C$17)), "")) -> 0.1299 | N81: =IF(K81="","",K81*(1+M81)) -> 1.1299 | O81: =K81*I81 -> 2 | P81: =N81*I81 -> 2.2598
... B95: 019.027 | E95: Reducao fd ff excentrica pn10 dn150 dn50 | G95: Mat | H95: CP | I95: 2 | J95: ud | K95: 1 | M95: =IF(G95="", "", IFERROR(IF(G95="Mat", BDI!C$31, IF(G95="MO", BDI!C$17)), "")) -> 0.1299 | N95: =IF(K95="","",K95*(1+M95)) -> 1.1299 | O95: =K95*I95 -> 2 | P95: =N95*I95 -> 2.2598
B96: 019.028 | E96: Conjunto motobomba submersivel para esgoto com kit pedestal e cem h=62mca q=11,32m3/h rend 0,41 p=16.85kw t=460v | G96: Mat | H96: CP | I96: 2 | J96: CJ | K96: =143780.8/2 -> 71890.4 | M96: =IF(G96="", "", IFERROR(IF(G96="Mat", BDI!C$31, IF(G96="MO", BDI!C$17)), "")) -> 0.1299 | N96: =IF(K96="","",K96*(1+M96)) -> 81228.963 | O96: =K96*I96 -> 143780.8 | P96: =N96*I96 -> 162457.93
B97: 019.029 | E97: Tubo fd k9 ff (solda interferencia) para esgoto pn10 medindo 1,00m dn200 | G97: Mat | H97: CP | I97: 1 | J97: ud | K97: 1 | M97: =IF(G97="", "", IFERROR(IF(G97="Mat", BDI!C$31, IF(G97="MO", BDI!C$17)), "")) -> 0.1299 | N97: =IF(K97="","",K97*(1+M97)) -> 1.1299 | O97: =K97*I97 -> 1 | P97: =N97*I97 -> 1.1299
B98: 019.030 | E98: Conjunto haste de prolongamento em aco inox 304 com 2 mancais fixacao lateral comprimento de 2,1 a 4,0 m pol1.1/4” | G98: Mat | H98: CP | I98: 2 | J98: CJ | K98: 1 | M98: =IF(G98="", "", IFERROR(IF(G98="Mat", BDI!C$31, IF(G98="MO", BDI!C$17)), "")) -> 0.1299 | N98: =IF(K98="","",K98*(1+M98)) -> 1.1299 | O98: =K98*I98 -> 2 | P98: =N98*I98 -> 2.2598
B99: 019.031 | E99: Curva fd ff 45 para esgoto pn10 dn200 | G99: Mat | H99: CP | I99: 1 | J99: ud | K99: 1 | M99: =IF(G99="", "", IFERROR(IF(G99="Mat", BDI!C$31, IF(G99="MO", BDI!C$17)), "")) -> 0.1299 | N99: =IF(K99="","",K99*(1+M99)) -> 1.1299 | O99: =K99*I99 -> 1 | P99: =N99*I99 -> 1.1299
B100: 019.032 | E100: Tubo fd k9 ff (solda interferencia) para esgoto pn10 medindo 2,00m dn150 l=1995 mm | G100: Mat | H100: CP | I100: 1 | J100: ud | K100: 1 | M100: =IF(G100="", "", IFERROR(IF(G100="Mat", BDI!C$31, IF(G100="MO", BDI!C$17)), "")) -> 0.1299 | N100: =IF(K100="","",K100*(1+M100)) -> 1.1299 | O100: =K100*I100 -> 1 | P100: =N100*I100 -> 1.1299
B101: 019.033 | E101: Flange aco carbono para colarinho pead epoxi iso 12944 320um c5m durabilidade alta ou pp (nbr 7675/15593) pn10 de160 dn150 | G101: Mat | H101: CP | I101: 1 | J101: ud | K101: 1 | M101: =IF(G101="", "", IFERROR(IF(G101="Mat", BDI!C$31, IF(G101="MO", BDI!C$17)), "")) -> 0.1299 | N101: =IF(K101="","",K101*(1+M101)) -> 1.1299 | O101: =K101*I101 -> 1 | P101: =N101*I101 -> 1.1299
B102: 019.034 | E102: Junta de vedacao para flange pn10 dn150 | G102: Mat | H102: CP | I102: 5 | J102: ud | K102: 1 | M102: =IF(G102="", "", IFERROR(IF(G102="Mat", BDI!C$31, IF(G102="MO", BDI!C$17)), "")) -> 0.1299 | N102: =IF(K102="","",K102*(1+M102)) -> 1.1299 | O102: =K102*I102 -> 5 | P102: =N102*I102 -> 5.6495
B103: 019.035 | E103: Junta de vedacao para flange pn10 dn200 | G103: Mat | H103: CP | I103: 2 | J103: ud | K103: 1 | M103: =IF(G103="", "", IFERROR(IF(G103="Mat", BDI!C$31, IF(G103="MO", BDI!C$17)), "")) -> 0.1299 | N103: =IF(K103="","",K103*(1+M103)) -> 1.1299 | O103: =K103*I103 -> 2 | P103: =N103*I103 -> 2.2598
B104: 019.036 | E104: Kit parafuso porca arruela lisa aco inox arruela vedacao furacao para esgoto pn10 nbr 7675 dn50 | G104: Mat | H104: CP | I104: 1 | J104: CJ | K104: 1 | M104: =IF(G104="", "", IFERROR(IF(G104="Mat", BDI!C$31, IF(G104="MO", BDI!C$17)), "")) -> 0.1299 | N104: =IF(K104="","",K104*(1+M104)) -> 1.1299 | O104: =K104*I104 -> 1 | P104: =N104*I104 -> 1.1299
B105: 019.037 | E105: Kit parafuso porca arruela lisa aco inox arruela vedacao furacao para esgoto pn10 nbr 7675 dn100 | G105: Mat | H105: CP | I105: 2 | J105: CJ | K105: 1 | M105: =IF(G105="", "", IFERROR(IF(G105="Mat", BDI!C$31, IF(G105="MO", BDI!C$17)), "")) -> 0.1299 | N105: =IF(K105="","",K105*(1+M105)) -> 1.1299 | O105: =K105*I105 -> 2 | P105: =N105*I105 -> 2.2598
B106: 019.038 | E106: Kit parafuso porca arruela lisa aco inox arruela vedacao furacao para esgoto pn10 nbr 7675 dn150 | G106: Mat | H106: CP | I106: 28 | J106: CJ | K106: 1 | M106: =IF(G106="", "", IFERROR(IF(G106="Mat", BDI!C$31, IF(G106="MO", BDI!C$17)), "")) -> 0.1299 | N106: =IF(K106="","",K106*(1+M106)) -> 1.1299 | O106: =K106*I106 -> 28 | P106: =N106*I106 -> 31.6372
B107: 019.039 | E107: Kit parafuso porca arruela lisa aco inox arruela vedacao furacao para esgoto pn10 nbr 7675 dn200 | G107: Mat | H107: CP | I107: 4 | J107: CJ | K107: 1 | M107: =IF(G107="", "", IFERROR(IF(G107="Mat", BDI!C$31, IF(G107="MO", BDI!C$17)), "")) -> 0.1299 | N107: =IF(K107="","",K107*(1+M107)) -> 1.1299 | O107: =K107*I107 -> 4 | P107: =N107*I107 -> 4.5196
B108: 019.040 | E108: Tubo pvc jei pb com anel coletor de esgoto (comprimentomontagem 2,62m) parede macica nbr 7362 ou nucleo celular nbr iso 21138-2 de 200 dn200 | G108: Mat | H108: CP | I108: 1 | J108: ud | K108: 1 | M108: =IF(G108="", "", IFERROR(IF(G108="Mat", BDI!C$31, IF(G108="MO", BDI!C$17)), "")) -> 0.1299 | N108: =IF(K108="","",K108*(1+M108)) -> 1.1299 | O108: =K108*I108 -> 1 | P108: =N108*I108 -> 1.1299
B109: 019.041 | E109: Tubo pvc jei pb com anel coletor de esgoto (comprimentomontagem 6m) parede macica nbr 7362 ou nucleo celular nbr iso 21138-2 de 200 dn200 | G109: Mat | H109: CP | I109: 2 | J109: ud | K109: 1 | M109: =IF(G109="", "", IFERROR(IF(G109="Mat", BDI!C$31, IF(G109="MO", BDI!C$17)), "")) -> 0.1299 | N109: =IF(K109="","",K109*(1+M109)) -> 1.1299 | O109: =K109*I109 -> 2 | P109: =N109*I109 -> 2.2598
B110: 014001002 | E110: Cmb submerso (poço profundo) 11 CV a 30 CV | G110: MO | H110: Sanepar | I110: 2 | J110: ud | K110: =[2]REF_TAB_PREÇOS_SANEPAR!I1332 -> 768.52 | M110: =IF(G110="", "", IFERROR(IF(G110="Mat", BDI!C$31, IF(G110="MO", BDI!C$17)), "")) -> 0.2449 | N110: =IF(K110="","",K110*(1+M110)) -> 956.73055 | O110: =K110*I110 -> 1537.04 | P110: =N110*I110 -> 1913.4611
B111: 019.048 | E111: Chave de nível tipo pera com contato NA+NF | G111: Mat | H111: CP | I111: 2 | J111: ud | K111: 1 | M111: =IF(G111="", "", IFERROR(IF(G111="Mat", BDI!C$31, IF(G111="MO", BDI!C$17)), "")) -> 0.1299 | N111: =IF(K111="","",K111*(1+M111)) -> 1.1299 | O111: =K111*I111 -> 2 | P111: =N111*I111 -> 2.2598
B112: 019.053 | E112: Tampa simples articulada prfv vao 0800 x 0800 mm | G112: Mat | H112: CP | I112: 5 | J112: ud | K112: 1 | M112: =IF(G112="", "", IFERROR(IF(G112="Mat", BDI!C$31, IF(G112="MO", BDI!C$17)), "")) -> 0.1299 | N112: =IF(K112="","",K112*(1+M112)) -> 1.1299 | O112: =K112*I112 -> 5 | P112: =N112*I112 -> 5.6495
B113: 019.054 | E113: Tampao fd ou fofo t-12 articulado passagem livre 130mm carga 12,5t para registro padrao sanepar | G113: Mat | H113: CP | I113: 2 | J113: ud | M113: =IF(G113="", "", IFERROR(IF(G113="Mat", BDI!C$31, IF(G113="MO", BDI!C$17)), "")) -> 0.1299 | N113: =IF(K113="","",K113*(1+M113)) | O113: =K113*I113 -> 0
B114: 019.055 | E114: Tampao fd ou fofo com tampa e aro grelhado classe 400 kn redondo passagem livre minimo 555mm articulado betume para poco visita dn 600 | G114: Mat | H114: CP | I114: 3 | J114: ud | K114: 1 | M114: =IF(G114="", "", IFERROR(IF(G114="Mat", BDI!C$31, IF(G114="MO", BDI!C$17)), "")) -> 0.1299 | N114: =IF(K114="","",K114*(1+M114)) -> 1.1299 | O114: =K114*I114 -> 3 | P114: =N114*I114 -> 3.3897
...

Sheet Quantitativo PA4
B3: DESCRIÇÃO | C3: QTD | D3: VALOR | E3: UNIDADE | F3: m
B4: TUBO POLIETILENO PE 100 PN10 FAIXA OCRE PARA ESGOTO (BARRA COM 6,0 M) DE16 - L=1600 mm | C4: 1 | E4: UN | F4: =1600/1000 -> 1.6
B5: COLARINHO POLIETILENO INJETADO TERMOFUSAO PE 100 PN10 DE160 | C5: 1 | D5: =285.99*1.1 -> 314.589 | E5: UN | G5: https://www.mercadolivre.com.br/colarinho-eletrofusao-pead-pe100-sdr11-160mm/up/MLBU1726017073
B6: TOCO DE TUBO FD FF PN10 MEDINDO 0.25M PARA ESGOTO DN150 | C6: 1 | E6: UN | F6: 0.25
B7: CONJUNTO MOTOBOMBA EM LINHA | C7: 1 | E7: CJ
B8: TE REDUCAO FD FFF PARA ESGOTO DN100 DN80 | C8: 1 | E8: UN
B9: VENTOSA COMBINADA/TRIPLICE FUNCAO PARA ESGOTO CORPO EM PRFV OU NYLON REFORCADO COM CAPACIDADE VAZAO MINIMA A 0,4 BAR DE 220,0 M3/H FLANGE PN10/16 DN100 POL4” | C9: 1 | D9: =12580*1.1 -> 13838 | E9: UN | G9: https://www.instaagro.com/ventosa-combinada-triplice-func-o-com-dispositivo-anti-golpe-sp-para-esgoto-residuos-industriais-mod-c50-g-sp-4-dn-100-flange-ansi-150-corpo-aco-inox-bermad?srsltid=AfmBOop5B4mg9HZO_ju3WRa5gO9kb0qHBmGykROg6e7s1PIsyfVWx_38
B10: TE FD FFF PARA ESGOTO PN10 DN80 | C10: 1 | E10: UN
B11: TOCO DE TUBO FD FF 700MM COM ABA DE VEDACAO PN10 PARA ESGOTO DN80 | C11: 1 | E11: UN | F11: =700/1000 -> 0.7
B12: COLARINHO POLIETILENO INJETADO TERMOFUSAO PE 100 PN10 DE90 | C12: 1 | E12: UN
B13: VALVULA GUILHOTINA BIDIRECIONAL FD LUG/SEMILUG/WAFER MANUAL CASTELO QUADRADO E VOLANTE PARA ESGOTO/AGUA BRUTA 10 BAR FURACAO PN10 HASTE PROL 0.01 A 1.0M DN80 | C13: 1 | E13: UN
B14: TUBO FD K9 PF (SOLDA INTERFERENCIA) PARA ESGOTO PN10 MEDINDO 1,26M DN150 | C14: 1 | D14: =F14*1602 -> 2018.52 | E14: UN | F14: 1.26
B15: TOCO DE TUBO FD FF 700MM COM ABA DE VEDACAO PN10 PARA ESGOTO DN80 | C15: 1 | E15: UN | F15: =700/1000 -> 0.7
B16: CURVA FD FF 22 PARA ESGOTO PN10 DN80 | C16: 1 | E16: UN
B17: TUBO FD K9 PF (SOLDA INTERFERENCIA) PARA ESGOTO PN10 MEDINDO 0,70M DN80 | C17: 1 | E17: UN | F17: 0.7
B18: CONJUNTO MOTOBOMBA SUBMERSIVELQ=22,9 M3/H | C18: 1 | E18: UN
B19: ADAPTADOR CURTO PPR80 BOLSA/ROSCA MACHO BSP TERMOFUSAO PN 10 DE 90 POL 3” | C19: 1 | D19: =94.05*1.2 -> 112.86 | E19: UN | G19: https://www.plastolandia.com.br/adaptador-curto-polipropileno-bolsa-rosca-preto-3-x-90-mm
B20: UNIAO PPR FLANGEADA DE90 PN10 | C20: 1 | D20: =664.69*1.1 -> 731.159 | E20: UN | G20: https://www.mercadolivre.com.br/uniao-ppr-flangeada-dn90-amanco/up/MLBU1476326669
B21: CURVA LONGA 90 POLIPROPILENO RANDOMICO (PPR) DE90 | C21: 1 | D21: =457.35*1.1 -> 503.085 | E21: UN | G21: https://www.mercadolivre.com.br/curva-ppr-verde-longa-90-x--90mm-topfusion/up/MLBU3621032319#polycard_client=search-desktop&be_origin=backend&search_layout=grid&position=2&type=product&tracking_id=0550b0ff-cd04-494d-9508-51b655be897c&wid=MLB4325259309&sid=search
B22: TUBO PPR80 JS PP TERMOFUSAO (BARRA COM 6,0 METROS) PN 10 DE 90 | C22: 1 | D22: =647.04-1.1 -> 645.94 | E22: UN | F22: 6 | G22: https://www.plastolandia.com.br/tubo-polipropileno-solda-preto-pn-10-90-mm-x-8-20-mm-x-6-m
B23: VALVULA GUILHOTINA BIDIRECIONAL FD LUG/SEMILUG/WAFER MANUAL CASTELO QUADRADO E VOLANTE PARA ESGOTO/AGUA BRUTA 10 BAR FURACAO PN10 DN100 | C23: 1 | D23: 2193 | E23: UN
B24: FLANGE ACO CARBONO COM FURACAO PARA COLARINHO PEAD EPOXI ISO 12944 320UM C5M DURABILIDADE ALTA OU PP (NBR 7675/15593) PN10 DE90 DN80 | C24: 1 | D24: =176.53*1.1 -> 194.183 | E24: CJ | G24: https://www.mercadolivre.com.br/flange-solto-aco-din-pn1016-para-colarinho-pead-110mm/up/MLBU1750777736
B25: FLANGE ACO CARBONO PARA COLARINHO PEAD EPOXI ISO 12944 320UM C5M DURABILIDADE ALTA OU PP (NBR 7675/15593) PN10 DE160 DN150 | C25: 1 | D25: 506.94 | E25: CJ
B26: KIT PARAFUSO PORCA ARRUELA LISA ACO CARBONO ARRUELA VEDACAO FURACAO PARA ESGOTO PN10 NBR 7675 PARA FLANGE AVULSA PARA COLARINHO PEAD DN80 | C26: 1 | E26: CJ
B27: KIT PARAFUSO PORCA ARRUELA LISA ACO CARBONO ARRUELA VEDACAO FURACAO PARA ESGOTO PN10 NBR 7675 PARA FLANGE AVULSA PARA COLARINHO PEAD DN150 | C27: 1 | E27: CJ
B28: KIT PARAFUSO PORCA ARRUELA LISA ACO CARBONO ARRUELA VEDACAO FURACAO PN10 PARA VALVULAS BORBOLETA WAFER AWWA C504 NBR 7675 DN80 | C28: 1 | E28: CJ
B29: KIT PARAFUSO PORCA ARRUELA LISA ACO CARBONO ARRUELA VEDACAO FURACAO PN10 PARA VALVULAS BORBOLETA WAFER AWWA C504 NBR 7675 DN100 | C29: 1 | E29: CJ
B30: KIT PARAFUSO PORCA ARRUELA LISA ACO INOX ARRUELA VEDACAO FURACAO PARA ESGOTO PN10 NBR 7675 DN80 | C30: 5 | E30: CJ
B31: KIT PARAFUSO PORCA ARRUELA LISA ACO INOX ARRUELA VEDACAO FURACAO PARA ESGOTO PN10 NBR 7675 DN100 | C31: 1 | E31: CJ
B32: KIT PARAFUSO PORCA ARRUELA LISA ACO INOX ARRUELA VEDACAO FURACAO PARA ESGOTO PN10 NBR 7675 DN150 | C32: 1 | E32: CJ
B33: Escada tipo marinheiro PRFV sem gaiola altura menor que 3,5m | C33: 1 | D33: =674.82*2 -> 1349.64 | E33: UN | G33: https://www.mercadolivre.com.br/escada-marinheiro-de-aluminio-200-m--cor-branca/up/MLBU1136718753
B35: Tubo polietileno PE 100 PN10 faixa ocre para esgoto (rolo com 50,0 m) DE90 | D35: =58.62*1.2 -> 70.344
B36: Curva polietileno injetada 45 termofusao PE 100 PN10 DE90 | D36: =405.81*1.1 -> 446.391 | G36: https://mininco.com.br/products/curva-45-termofusao-pead-pn8-de-90mm-1?_pos=2&_sid=1553216d8&_ss=r
B37: Curva polietileno injetada 90 termofusao PE 100 PN10 DE90 | D37: =599.54*1.1 -> 659.494 | G37: https://mininco.com.br/products/curva-90-termofusao-pead-pn10-de-90mm?_pos=1&_sid=1553216d8&_ss=r
B38: Curva polietileno injetada 30 termofusao PE 100 PN10 DE90 | D38: 417.65
B39: Joelho ajustavel 0 a 12 graus polietileno PE 100 BP PN16 para eletrofusao DE90 | D39: 1141.2
B42: tubo polietileno pe 100 pn10 faixa ocre para esgoto (barra com 6,0 m) de16 - l=1600 mm | C42: 1
B43: colarinho polietileno injetado termofusao pe 100 pn10 de160 | C43: 1
B44: toco de tubo fd ff pn10 medindo 0.25m para esgoto dn150 | C44: 1
B45: conjunto motobomba em linha | C45: 1
B46: te reducao fd fff para esgoto dn100 dn80 | C46: 1
B47: ventosa combinada/triplice funcao para esgoto corpo em prfv ou nylon reforcado com capacidade vazao minima a 0,4 bar de 220,0 m3/h flange pn10/16 dn100 pol4” | C47: 1
B48: te fd fff para esgoto pn10 dn80 | C48: 1
B49: toco de tubo fd ff 700mm com aba de vedacao pn10 para esgoto dn80 | C49: 1
B50: colarinho polietileno injetado termofusao pe 100 pn10 de90 | C50: 1
B51: valvula guilhotina bidirecional fd lug/semilug/wafer manual castelo quadrado e volante para esgoto/agua bruta 10 bar furacao pn10 haste prol 0.01 a 1.0m dn80 | C51: 1
B52: tubo fd k9 pf (solda interferencia) para esgoto pn10 medindo 1,26m dn150 | C52: 1
B53: toco de tubo fd ff 700mm com aba de vedacao pn10 para esgoto dn80 | C53: 1
... B70: kit parafuso porca arruela lisa aco inox arruela vedacao furacao para esgoto pn10 nbr 7675 dn150 | C70: 1
B76: =LOWER(D76) -> flange aco carbono para colarinho pead epoxi iso 12944 320um c5m durabilidade alta ou pp (nbr 7675/15593) pn16 de110 dn100 | D76: FLANGE ACO CARBONO PARA COLARINHO PEAD EPOXI ISO 12944 320UM C5M DURABILIDADE ALTA OU PP (NBR 7675/15593) PN16 DE110 DN100
B77: =LOWER(D77) -> kit parafuso porca arruela lisa aco carbono arruela vedacao furacao para esgoto pn10 nbr 7675 para flange avulsa para colarinho pead dn150 | D77: KIT PARAFUSO PORCA ARRUELA LISA ACO CARBONO ARRUELA VEDACAO FURACAO PARA ESGOTO PN10 NBR 7675 PARA FLANGE AVULSA PARA COLARINHO PEAD DN150
B78: =LOWER(D78) -> kit parafuso porca arruela lisa aco carbono arruela vedacao furacao para esgoto pn16 nbr 7675 para flange avulsa para colarinho pead dn100 | D78: KIT PARAFUSO PORCA ARRUELA LISA ACO CARBONO ARRUELA VEDACAO FURACAO PARA ESGOTO PN16 NBR 7675 PARA FLANGE AVULSA PARA COLARINHO PEAD DN100
B79: =LOWER(D79) -> kit parafuso porca arruela lisa aco carbono arruela vedacao furacao pn16 nbr 7675 dn80 | D79: KIT PARAFUSO PORCA ARRUELA LISA ACO CARBONO ARRUELA VEDACAO FURACAO PN16 NBR 7675 DN80
B80: =LOWER(D80) -> kit parafuso porca arruela lisa aco carbono arruela vedacao furacao pn16 nbr 7675 dn100 | D80: KIT PARAFUSO PORCA ARRUELA LISA ACO CARBONO ARRUELA VEDACAO FURACAO PN16 NBR 7675 DN100
B81: =LOWER(D81) -> kit parafuso porca arruela lisa aco carbono arruela vedacao furacao pn16 para valvulas borboleta wafer awwa c504 nbr 7675 dn80 | D81: KIT PARAFUSO PORCA ARRUELA LISA ACO CARBONO ARRUELA VEDACAO FURACAO PN16 PARA VALVULAS BORBOLETA WAFER AWWA C504 NBR 7675 DN80
B82: =LOWER(D82) -> kit parafuso porca arruela lisa aco inox arruela vedacao furacao para esgoto pn10 nbr 7675 dn150 | D82: KIT PARAFUSO PORCA ARRUELA LISA ACO INOX ARRUELA VEDACAO FURACAO PARA ESGOTO PN10 NBR 7675 DN150
B83: =LOWER(D83) -> extremidade fd pf 700mm com aba de vedacao para esgoto pn16 dn80 | D83: EXTREMIDADE FD PF 700MM COM ABA DE VEDACAO PARA ESGOTO PN16 DN80
